<?xml version='1.0' encoding='UTF-8'?><ern:NewReleaseMessage xmlns:ern="http://ddex.net/xml/ern/382" xmlns:xs="http://www.w3.org/2001/XMLSchema-instance" xs:schemaLocation="http://ddex.net/xml/ern/382 http://ddex.net/xml/ern/382/release-notification.xsd" MessageSchemaVersionId="ern/382">
		<MessageHeader>
		    <MessageThreadId>723524</MessageThreadId>
		    <MessageId>9BFFE4C4BF2F487F31528AC475AB82FE</MessageId>
		    <MessageSender>
		      <PartyId>PADPIDA2012091204O</PartyId>
		      <PartyName>
		        <FullName>Routenote</FullName>
		      </PartyName>
		    </MessageSender>
		    <MessageRecipient>
		      <PartyId>PADPIDA2011021513H</PartyId>
		      <PartyName>
		        <FullName>DEEZER</FullName>
		      </PartyName>
		    </MessageRecipient>
		    <MessageCreatedDateTime>2025-04-29T07:52:53Z</MessageCreatedDateTime>
		    <MessageControlType>LiveMessage</MessageControlType>
		  </MessageHeader><UpdateIndicator xmlns=''>OriginalMessage</UpdateIndicator><ResourceList><SoundRecording>
				      <SoundRecordingType>MusicalWorkSoundRecording</SoundRecordingType>
				      <SoundRecordingId>
				        <ISRC>GX38U2583836</ISRC>
				      </SoundRecordingId>
				      <ResourceReference>A1</ResourceReference>
				      <ReferenceTitle>
				        <TitleText>Ori</TitleText></ReferenceTitle>
				      <Duration>PT0H3M13S</Duration>
				      <SoundRecordingDetailsByTerritory>
				        <TerritoryCode>Worldwide</TerritoryCode><Title TitleType='FormalTitle'>
						  <TitleText>Ori</TitleText>
						</Title>
						<Title TitleType='DisplayTitle'>
						  <TitleText>Ori</TitleText>
						</Title><DisplayArtist>
							<PartyName>
							<FullName>Atayese itana ogo</FullName>
							</PartyName><ArtistRole>MainArtist</ArtistRole></DisplayArtist>
									<IndirectResourceContributor>
											<PartyName>
												<FullName>Atayese Itana ogo</FullName>
											</PartyName>
											<IndirectResourceContributorRole>Composer</IndirectResourceContributorRole>
										</IndirectResourceContributor>
							<LabelName>Atayese itana ogo music world</LabelName>
							<OriginalResourceReleaseDate>2025-04-12</OriginalResourceReleaseDate>
							<PLine>
							<Year>2025</Year>
							<PLineText>Atayese itana ogo</PLineText>
						 </PLine>
				        <Genre>
				          <GenreText>Christian &amp; Gospel</GenreText>
						  <SubGenre>Alternative</SubGenre>
				        </Genre>
						<ParentalWarningType>NotExplicit</ParentalWarningType>
				        <TechnicalSoundRecordingDetails>
					          <TechnicalResourceDetailsReference>T1</TechnicalResourceDetailsReference>
					          <AudioCodecType UserDefinedValue='FLAC'>UserDefined</AudioCodecType>
					          <SamplingRate UnitOfMeasure='kHz'>44100</SamplingRate>
							  <BitsPerSample>16</BitsPerSample>
					          <IsPreview>false</IsPreview>
					          <File>
					            <FileName>5063710578394_001.flac</FileName>
					            <FilePath>resources/</FilePath>
								<HashSum>
					              <HashSum>a71321b0733c706263521aa2fe8614db</HashSum>
					              <HashSumAlgorithmType>MD5</HashSumAlgorithmType>
								</HashSum>
					          </File>
					        </TechnicalSoundRecordingDetails></SoundRecordingDetailsByTerritory>
				    </SoundRecording><SoundRecording>
				      <SoundRecordingType>MusicalWorkSoundRecording</SoundRecordingType>
				      <SoundRecordingId>
				        <ISRC>GX38U2566942</ISRC>
				      </SoundRecordingId>
				      <ResourceReference>A2</ResourceReference>
				      <ReferenceTitle>
				        <TitleText>Halleluyah</TitleText></ReferenceTitle>
				      <Duration>PT0H4M05S</Duration>
				      <SoundRecordingDetailsByTerritory>
				        <TerritoryCode>Worldwide</TerritoryCode><Title TitleType='FormalTitle'>
						  <TitleText>Halleluyah</TitleText>
						</Title>
						<Title TitleType='DisplayTitle'>
						  <TitleText>Halleluyah</TitleText>
						</Title><DisplayArtist>
							<PartyName>
							<FullName>Atayese itana ogo</FullName>
							</PartyName><ArtistRole>MainArtist</ArtistRole></DisplayArtist>
									<IndirectResourceContributor>
											<PartyName>
												<FullName>Atayese Itana ogo</FullName>
											</PartyName>
											<IndirectResourceContributorRole>Composer</IndirectResourceContributorRole>
										</IndirectResourceContributor>
							<LabelName>Atayese itana ogo music world</LabelName>
							<OriginalResourceReleaseDate>2025-04-12</OriginalResourceReleaseDate>
							<PLine>
							<Year>2025</Year>
							<PLineText>Atayese itana ogo</PLineText>
						 </PLine>
				        <Genre>
				          <GenreText>Christian &amp; Gospel</GenreText>
						  <SubGenre>Alternative</SubGenre>
				        </Genre>
						<ParentalWarningType>NotExplicit</ParentalWarningType>
				        <TechnicalSoundRecordingDetails>
					          <TechnicalResourceDetailsReference>T2</TechnicalResourceDetailsReference>
					          <AudioCodecType UserDefinedValue='FLAC'>UserDefined</AudioCodecType>
					          <SamplingRate UnitOfMeasure='kHz'>44100</SamplingRate>
							  <BitsPerSample>16</BitsPerSample>
					          <IsPreview>false</IsPreview>
					          <File>
					            <FileName>5063710578394_002.flac</FileName>
					            <FilePath>resources/</FilePath>
								<HashSum>
					              <HashSum>e2a95329ad14ad79de8cc5481c14d3fe</HashSum>
					              <HashSumAlgorithmType>MD5</HashSumAlgorithmType>
								</HashSum>
					          </File>
					        </TechnicalSoundRecordingDetails></SoundRecordingDetailsByTerritory>
				    </SoundRecording><SoundRecording>
				      <SoundRecordingType>MusicalWorkSoundRecording</SoundRecordingType>
				      <SoundRecordingId>
				        <ISRC>GX38U2573301</ISRC>
				      </SoundRecordingId>
				      <ResourceReference>A3</ResourceReference>
				      <ReferenceTitle>
				        <TitleText>Gbo adurami</TitleText></ReferenceTitle>
				      <Duration>PT0H8M25S</Duration>
				      <SoundRecordingDetailsByTerritory>
				        <TerritoryCode>Worldwide</TerritoryCode><Title TitleType='FormalTitle'>
						  <TitleText>Gbo adurami</TitleText>
						</Title>
						<Title TitleType='DisplayTitle'>
						  <TitleText>Gbo adurami</TitleText>
						</Title><DisplayArtist>
							<PartyName>
							<FullName>Atayese itana ogo</FullName>
							</PartyName><ArtistRole>MainArtist</ArtistRole></DisplayArtist>
									<IndirectResourceContributor>
											<PartyName>
												<FullName>Atayese Itana ogo</FullName>
											</PartyName>
											<IndirectResourceContributorRole>Composer</IndirectResourceContributorRole>
										</IndirectResourceContributor>
							<LabelName>Atayese itana ogo music world</LabelName>
							<OriginalResourceReleaseDate>2025-04-12</OriginalResourceReleaseDate>
							<PLine>
							<Year>2025</Year>
							<PLineText>Atayese itana ogo</PLineText>
						 </PLine>
				        <Genre>
				          <GenreText>Christian &amp; Gospel</GenreText>
						  <SubGenre>Alternative</SubGenre>
				        </Genre>
						<ParentalWarningType>NotExplicit</ParentalWarningType>
				        <TechnicalSoundRecordingDetails>
					          <TechnicalResourceDetailsReference>T3</TechnicalResourceDetailsReference>
					          <AudioCodecType UserDefinedValue='FLAC'>UserDefined</AudioCodecType>
					          <SamplingRate UnitOfMeasure='kHz'>44100</SamplingRate>
							  <BitsPerSample>16</BitsPerSample>
					          <IsPreview>false</IsPreview>
					          <File>
					            <FileName>5063710578394_003.flac</FileName>
					            <FilePath>resources/</FilePath>
								<HashSum>
					              <HashSum>15f4b231cfd38dfbc563b9e7d8265840</HashSum>
					              <HashSumAlgorithmType>MD5</HashSumAlgorithmType>
								</HashSum>
					          </File>
					        </TechnicalSoundRecordingDetails></SoundRecordingDetailsByTerritory>
				    </SoundRecording><Image>
			      <ImageType>FrontCoverImage</ImageType>
			      <ImageId>
			        <ProprietaryId Namespace='CDB'>GGL_UIM_ID:[5063710578394.jpg]</ProprietaryId>
			      </ImageId>
			      <ResourceReference>A4</ResourceReference>
			      <ImageDetailsByTerritory>
			        <TerritoryCode>Worldwide</TerritoryCode><TechnicalImageDetails>
			          <TechnicalResourceDetailsReference>T1</TechnicalResourceDetailsReference>
			          <ImageCodecType>JPEG</ImageCodecType>
			          <ImageHeight>3000</ImageHeight>
			          <ImageWidth>3000</ImageWidth>
			          <File>
			            <FileName>5063710578394.jpg</FileName>
			            <FilePath>resources/</FilePath>
			            <HashSum>
			              <HashSum>bf33e658b1866226d27bc573a1005528</HashSum>
			              <HashSumAlgorithmType>MD5</HashSumAlgorithmType>
			            </HashSum>
			          </File>
					</TechnicalImageDetails></ImageDetailsByTerritory>
			    </Image></ResourceList><ReleaseList><Release>
		      <ReleaseId>
		        <ISRC>GX38U2583836</ISRC>
		      </ReleaseId>
		      <ReleaseReference>R1</ReleaseReference>
		      <ReferenceTitle>
		        <TitleText>Ori</TitleText></ReferenceTitle>
		      <ReleaseResourceReferenceList>
		        <ReleaseResourceReference ReleaseResourceType='PrimaryResource'>A1</ReleaseResourceReference>
		      </ReleaseResourceReferenceList>
		      <ReleaseType>TrackRelease</ReleaseType>
		      <ReleaseDetailsByTerritory>
		        <TerritoryCode>Worldwide</TerritoryCode>
		        <DisplayArtistName>Atayese itana ogo</DisplayArtistName>
		        <LabelName>Atayese itana ogo music world</LabelName><Title TitleType='FormalTitle'>
		          <TitleText>Ori</TitleText>
		        </Title>
		        <Title TitleType='DisplayTitle'>
		          <TitleText>Ori</TitleText>
		        </Title><DisplayArtist>
							<PartyName>
							<FullName>Atayese itana ogo</FullName>
							</PartyName><ArtistRole>MainArtist</ArtistRole></DisplayArtist>
					 <Genre>
		          <GenreText>Christian &amp; Gospel</GenreText>
				  <SubGenre>Alternative</SubGenre>
		        </Genre>
		        <OriginalReleaseDate>2025-04-12</OriginalReleaseDate>
		      </ReleaseDetailsByTerritory>
			<PLine>
				<Year>2025</Year>
				<PLineText>Atayese itana ogo</PLineText>
			 </PLine>
			 <CLine>
				<Year>2025</Year>
				<CLineText>Atayese itana ogo</CLineText>
			</CLine>
			</Release>
		    <Release>
		      <ReleaseId>
		        <ISRC>GX38U2566942</ISRC>
		      </ReleaseId>
		      <ReleaseReference>R2</ReleaseReference>
		      <ReferenceTitle>
		        <TitleText>Halleluyah</TitleText></ReferenceTitle>
		      <ReleaseResourceReferenceList>
		        <ReleaseResourceReference ReleaseResourceType='PrimaryResource'>A2</ReleaseResourceReference>
		      </ReleaseResourceReferenceList>
		      <ReleaseType>TrackRelease</ReleaseType>
		      <ReleaseDetailsByTerritory>
		        <TerritoryCode>Worldwide</TerritoryCode>
		        <DisplayArtistName>Atayese itana ogo</DisplayArtistName>
		        <LabelName>Atayese itana ogo music world</LabelName><Title TitleType='FormalTitle'>
		          <TitleText>Halleluyah</TitleText>
		        </Title>
		        <Title TitleType='DisplayTitle'>
		          <TitleText>Halleluyah</TitleText>
		        </Title><DisplayArtist>
							<PartyName>
							<FullName>Atayese itana ogo</FullName>
							</PartyName><ArtistRole>MainArtist</ArtistRole></DisplayArtist>
					 <Genre>
		          <GenreText>Christian &amp; Gospel</GenreText>
				  <SubGenre>Alternative</SubGenre>
		        </Genre>
		        <OriginalReleaseDate>2025-04-12</OriginalReleaseDate>
		      </ReleaseDetailsByTerritory>
			<PLine>
				<Year>2025</Year>
				<PLineText>Atayese itana ogo</PLineText>
			 </PLine>
			 <CLine>
				<Year>2025</Year>
				<CLineText>Atayese itana ogo</CLineText>
			</CLine>
			</Release>
		    <Release>
		      <ReleaseId>
		        <ISRC>GX38U2573301</ISRC>
		      </ReleaseId>
		      <ReleaseReference>R3</ReleaseReference>
		      <ReferenceTitle>
		        <TitleText>Gbo adurami</TitleText></ReferenceTitle>
		      <ReleaseResourceReferenceList>
		        <ReleaseResourceReference ReleaseResourceType='PrimaryResource'>A3</ReleaseResourceReference>
		      </ReleaseResourceReferenceList>
		      <ReleaseType>TrackRelease</ReleaseType>
		      <ReleaseDetailsByTerritory>
		        <TerritoryCode>Worldwide</TerritoryCode>
		        <DisplayArtistName>Atayese itana ogo</DisplayArtistName>
		        <LabelName>Atayese itana ogo music world</LabelName><Title TitleType='FormalTitle'>
		          <TitleText>Gbo adurami</TitleText>
		        </Title>
		        <Title TitleType='DisplayTitle'>
		          <TitleText>Gbo adurami</TitleText>
		        </Title><DisplayArtist>
							<PartyName>
							<FullName>Atayese itana ogo</FullName>
							</PartyName><ArtistRole>MainArtist</ArtistRole></DisplayArtist>
					 <Genre>
		          <GenreText>Christian &amp; Gospel</GenreText>
				  <SubGenre>Alternative</SubGenre>
		        </Genre>
		        <OriginalReleaseDate>2025-04-12</OriginalReleaseDate>
		      </ReleaseDetailsByTerritory>
			<PLine>
				<Year>2025</Year>
				<PLineText>Atayese itana ogo</PLineText>
			 </PLine>
			 <CLine>
				<Year>2025</Year>
				<CLineText>Atayese itana ogo</CLineText>
			</CLine>
			</Release>
		    <Release IsMainRelease='true'>
		      <ReleaseId><ICPN IsEan='true'>5063710578394</ICPN><CatalogNumber Namespace='CDB'>Atayeseitanaogo</CatalogNumber></ReleaseId><ReleaseReference>R0</ReleaseReference>
			<ReferenceTitle><TitleText>Itana ogo</TitleText></ReferenceTitle><ReleaseResourceReferenceList>
			  <ReleaseResourceReference ReleaseResourceType='PrimaryResource'>A1</ReleaseResourceReference>
			  
			  <ReleaseResourceReference ReleaseResourceType='PrimaryResource'>A2</ReleaseResourceReference>
			  
			  <ReleaseResourceReference ReleaseResourceType='PrimaryResource'>A3</ReleaseResourceReference>
			    <ReleaseResourceReference ReleaseResourceType='SecondaryResource'>A4</ReleaseResourceReference></ReleaseResourceReferenceList><ReleaseType>Album</ReleaseType> <ReleaseDetailsByTerritory>
		        <TerritoryCode>Worldwide</TerritoryCode>
		        <DisplayArtistName>Atayese itana ogo</DisplayArtistName>
		        <LabelName>Atayese itana ogo music world</LabelName>
					<Title TitleType='FormalTitle'>
					  <TitleText>Itana ogo</TitleText>
					</Title>
					<Title TitleType='DisplayTitle'>
					  <TitleText>Itana ogo</TitleText>
					</Title><DisplayArtist>
							<PartyName>
							<FullName>Atayese itana ogo</FullName>
							</PartyName><ArtistRole>MainArtist</ArtistRole></DisplayArtist>
		        <ParentalWarningType>NotExplicit</ParentalWarningType>
				<ResourceGroup>
					<ResourceGroup>
						<Title TitleType='GroupingTitle'>
				          <TitleText>Itana ogo</TitleText>
				  </Title><SequenceNumber>1</SequenceNumber><ResourceGroupContentItem>
				<SequenceNumber>1</SequenceNumber>
				<ResourceType>SoundRecording</ResourceType>
				<ReleaseResourceReference>A1</ReleaseResourceReference>
				</ResourceGroupContentItem><ResourceGroupContentItem>
				<SequenceNumber>2</SequenceNumber>
				<ResourceType>SoundRecording</ResourceType>
				<ReleaseResourceReference>A2</ReleaseResourceReference>
				</ResourceGroupContentItem><ResourceGroupContentItem>
				<SequenceNumber>3</SequenceNumber>
				<ResourceType>SoundRecording</ResourceType>
				<ReleaseResourceReference>A3</ReleaseResourceReference>
				</ResourceGroupContentItem> </ResourceGroup>
				  <ResourceGroupContentItem>
				 <ResourceType>Image</ResourceType>
				<ReleaseResourceReference>A4</ReleaseResourceReference>
				</ResourceGroupContentItem>
				</ResourceGroup>
		        <Genre>
		          <GenreText>Christian &amp; Gospel</GenreText>
				  <SubGenre>Alternative</SubGenre>
		        </Genre>
		        <OriginalReleaseDate>2025-04-12</OriginalReleaseDate>
		      </ReleaseDetailsByTerritory>
			<PLine>
				<Year>2025</Year>
				<PLineText>Atayese itana ogo</PLineText>
			 </PLine>
			 <CLine>
				<Year>2025</Year>
				<CLineText>Atayese itana ogo</CLineText>
			</CLine>
		    </Release></ReleaseList>
		  <DealList>
		    <ReleaseDeal>
		      <DealReleaseReference>R0</DealReleaseReference>
               <Deal>
		        <DealTerms>
					<CommercialModelType>PayAsYouGoModel</CommercialModelType>
                    <CommercialModelType>AdvertisementSupportedModel</CommercialModelType>
                     <CommercialModelType>SubscriptionModel</CommercialModelType> 
		         <Usage> 
                     <UseType>PermanentDownload</UseType> 
                     <UseType>OnDemandStream</UseType> 
                      <UseType>NonInteractiveStream</UseType> 
                      <DistributionChannelType>InternetAndMobile</DistributionChannelType> 
                 </Usage> 
					<TerritoryCode>Worldwide</TerritoryCode>
					<ValidityPeriod><StartDateTime>2025-04-21T00:00:00</StartDateTime></ValidityPeriod>
		        </DealTerms>
			</Deal>
		    </ReleaseDeal>
			<ReleaseDeal>
		      <DealReleaseReference>R1</DealReleaseReference>
		      <Deal>
		        <DealTerms>
					<CommercialModelType>PayAsYouGoModel</CommercialModelType>
                    <CommercialModelType>AdvertisementSupportedModel</CommercialModelType>
                    <CommercialModelType>SubscriptionModel</CommercialModelType> 
					<Usage> 
						 <UseType>PermanentDownload</UseType> 
                          <UseType>OnDemandStream</UseType> 
                          <UseType>NonInteractiveStream</UseType> 
                          <DistributionChannelType>InternetAndMobile</DistributionChannelType> 
                      </Usage>
					<TerritoryCode>Worldwide</TerritoryCode>
					<ValidityPeriod><StartDateTime>2025-04-21T00:00:00</StartDateTime></ValidityPeriod>
		        </DealTerms>
			</Deal>				  		      
		    </ReleaseDeal>
			<ReleaseDeal>
		      <DealReleaseReference>R2</DealReleaseReference>
		      <Deal>
		        <DealTerms>
					<CommercialModelType>PayAsYouGoModel</CommercialModelType>
                    <CommercialModelType>AdvertisementSupportedModel</CommercialModelType>
                    <CommercialModelType>SubscriptionModel</CommercialModelType> 
					<Usage> 
						 <UseType>PermanentDownload</UseType> 
                          <UseType>OnDemandStream</UseType> 
                          <UseType>NonInteractiveStream</UseType> 
                          <DistributionChannelType>InternetAndMobile</DistributionChannelType> 
                      </Usage>
					<TerritoryCode>Worldwide</TerritoryCode>
					<ValidityPeriod><StartDateTime>2025-04-21T00:00:00</StartDateTime></ValidityPeriod>
		        </DealTerms>
			</Deal>				  		      
		    </ReleaseDeal>
			<ReleaseDeal>
		      <DealReleaseReference>R3</DealReleaseReference>
		      <Deal>
		        <DealTerms>
					<CommercialModelType>PayAsYouGoModel</CommercialModelType>
                    <CommercialModelType>AdvertisementSupportedModel</CommercialModelType>
                    <CommercialModelType>SubscriptionModel</CommercialModelType> 
					<Usage> 
						 <UseType>PermanentDownload</UseType> 
                          <UseType>OnDemandStream</UseType> 
                          <UseType>NonInteractiveStream</UseType> 
                          <DistributionChannelType>InternetAndMobile</DistributionChannelType> 
                      </Usage>
					<TerritoryCode>Worldwide</TerritoryCode>
					<ValidityPeriod><StartDateTime>2025-04-21T00:00:00</StartDateTime></ValidityPeriod>
		        </DealTerms>
			</Deal>				  		      
		    </ReleaseDeal>
			</DealList></ern:NewReleaseMessage>