<?xml version='1.0' encoding='UTF-8'?><ern:NewReleaseMessage xmlns:ern="http://ddex.net/xml/ern/382" xmlns:xs="http://www.w3.org/2001/XMLSchema-instance" xs:schemaLocation="http://ddex.net/xml/ern/382 http://ddex.net/xml/ern/382/release-notification.xsd" MessageSchemaVersionId="ern/382">
		<MessageHeader>
		    <MessageThreadId>723524</MessageThreadId>
		    <MessageId>5D9E6AB792F79BC569582504C0410BB9</MessageId>
		    <MessageSender>
		      <PartyId>PADPIDA2012091204O</PartyId>
		      <PartyName>
		        <FullName>Routenote</FullName>
		      </PartyName>
		    </MessageSender>
		    <MessageRecipient>
		      <PartyId>PADPIDA2011021513H</PartyId>
		      <PartyName>
		        <FullName>DEEZER</FullName>
		      </PartyName>
		    </MessageRecipient>
		    <MessageCreatedDateTime>2025-04-29T07:51:09Z</MessageCreatedDateTime>
		    <MessageControlType>LiveMessage</MessageControlType>
		  </MessageHeader><UpdateIndicator xmlns=''>OriginalMessage</UpdateIndicator><ResourceList><SoundRecording>
				      <SoundRecordingType>MusicalWorkSoundRecording</SoundRecordingType>
				      <SoundRecordingId>
				        <ISRC>GX38U2569046</ISRC>
				      </SoundRecordingId>
				      <ResourceReference>A1</ResourceReference>
				      <ReferenceTitle>
				        <TitleText>One Day I Wrote Her Name Upon the Strand</TitleText></ReferenceTitle>
				      <Duration>PT0H4M01S</Duration>
				      <SoundRecordingDetailsByTerritory>
				        <TerritoryCode>Worldwide</TerritoryCode><Title TitleType='FormalTitle'>
						  <TitleText>One Day I Wrote Her Name Upon the Strand</TitleText>
						</Title>
						<Title TitleType='DisplayTitle'>
						  <TitleText>One Day I Wrote Her Name Upon the Strand</TitleText>
						</Title><DisplayArtist>
							<PartyName>
							<FullName>Poets of Rock</FullName>
							</PartyName><ArtistRole>MainArtist</ArtistRole></DisplayArtist>
									<IndirectResourceContributor>
											<PartyName>
												<FullName>Mark Wenig</FullName>
											</PartyName>
											<IndirectResourceContributorRole>Composer</IndirectResourceContributorRole>
										</IndirectResourceContributor>
								<IndirectResourceContributor>
										<PartyName>
											<FullName>Edmund Spenser</FullName>
										</PartyName>
										<IndirectResourceContributorRole>Lyricist</IndirectResourceContributorRole>
									</IndirectResourceContributor> 
							<LabelName>Poets of Rock</LabelName>
							<OriginalResourceReleaseDate>2025-04-10</OriginalResourceReleaseDate>
							<PLine>
							<Year>2025</Year>
							<PLineText>Mark Wenig</PLineText>
						 </PLine>
				        <Genre>
				          <GenreText>Rock</GenreText>
						  <SubGenre>None</SubGenre>
				        </Genre>
						<ParentalWarningType>NotExplicit</ParentalWarningType>
				        <TechnicalSoundRecordingDetails>
					          <TechnicalResourceDetailsReference>T1</TechnicalResourceDetailsReference>
					          <AudioCodecType UserDefinedValue='FLAC'>UserDefined</AudioCodecType>
					          <SamplingRate UnitOfMeasure='kHz'>44100</SamplingRate>
							  <BitsPerSample>16</BitsPerSample>
					          <IsPreview>false</IsPreview>
					          <File>
					            <FileName>5063740193321_001.flac</FileName>
					            <FilePath>resources/</FilePath>
								<HashSum>
					              <HashSum>2c65691037785637881db9226f32e464</HashSum>
					              <HashSumAlgorithmType>MD5</HashSumAlgorithmType>
								</HashSum>
					          </File>
					        </TechnicalSoundRecordingDetails></SoundRecordingDetailsByTerritory>
				    </SoundRecording><SoundRecording>
				      <SoundRecordingType>MusicalWorkSoundRecording</SoundRecordingType>
				      <SoundRecordingId>
				        <ISRC>GX38U2538353</ISRC>
				      </SoundRecordingId>
				      <ResourceReference>A2</ResourceReference>
				      <ReferenceTitle>
				        <TitleText>I Wandered Lonely as a Cloud</TitleText></ReferenceTitle>
				      <Duration>PT0H4M05S</Duration>
				      <SoundRecordingDetailsByTerritory>
				        <TerritoryCode>Worldwide</TerritoryCode><Title TitleType='FormalTitle'>
						  <TitleText>I Wandered Lonely as a Cloud</TitleText>
						</Title>
						<Title TitleType='DisplayTitle'>
						  <TitleText>I Wandered Lonely as a Cloud</TitleText>
						</Title><DisplayArtist>
							<PartyName>
							<FullName>Poets of Rock</FullName>
							</PartyName><ArtistRole>MainArtist</ArtistRole></DisplayArtist>
									<IndirectResourceContributor>
											<PartyName>
												<FullName>Mark Wenig</FullName>
											</PartyName>
											<IndirectResourceContributorRole>Composer</IndirectResourceContributorRole>
										</IndirectResourceContributor>
								<IndirectResourceContributor>
										<PartyName>
											<FullName>William Wordsworth</FullName>
										</PartyName>
										<IndirectResourceContributorRole>Lyricist</IndirectResourceContributorRole>
									</IndirectResourceContributor> 
							<LabelName>Poets of Rock</LabelName>
							<OriginalResourceReleaseDate>2025-04-10</OriginalResourceReleaseDate>
							<PLine>
							<Year>2025</Year>
							<PLineText>Mark Wenig</PLineText>
						 </PLine>
				        <Genre>
				          <GenreText>Rock</GenreText>
						  <SubGenre>None</SubGenre>
				        </Genre>
						<ParentalWarningType>NotExplicit</ParentalWarningType>
				        <TechnicalSoundRecordingDetails>
					          <TechnicalResourceDetailsReference>T2</TechnicalResourceDetailsReference>
					          <AudioCodecType UserDefinedValue='FLAC'>UserDefined</AudioCodecType>
					          <SamplingRate UnitOfMeasure='kHz'>44100</SamplingRate>
							  <BitsPerSample>16</BitsPerSample>
					          <IsPreview>false</IsPreview>
					          <File>
					            <FileName>5063740193321_002.flac</FileName>
					            <FilePath>resources/</FilePath>
								<HashSum>
					              <HashSum>46721a85bdad39d4d087b8b079f0074f</HashSum>
					              <HashSumAlgorithmType>MD5</HashSumAlgorithmType>
								</HashSum>
					          </File>
					        </TechnicalSoundRecordingDetails></SoundRecordingDetailsByTerritory>
				    </SoundRecording><SoundRecording>
				      <SoundRecordingType>MusicalWorkSoundRecording</SoundRecordingType>
				      <SoundRecordingId>
				        <ISRC>GX38U2501130</ISRC>
				      </SoundRecordingId>
				      <ResourceReference>A3</ResourceReference>
				      <ReferenceTitle>
				        <TitleText>Hope</TitleText></ReferenceTitle>
				      <Duration>PT0H3M27S</Duration>
				      <SoundRecordingDetailsByTerritory>
				        <TerritoryCode>Worldwide</TerritoryCode><Title TitleType='FormalTitle'>
						  <TitleText>Hope</TitleText>
						</Title>
						<Title TitleType='DisplayTitle'>
						  <TitleText>Hope</TitleText>
						</Title><DisplayArtist>
							<PartyName>
							<FullName>Poets of Rock</FullName>
							</PartyName><ArtistRole>MainArtist</ArtistRole></DisplayArtist>
									<IndirectResourceContributor>
											<PartyName>
												<FullName>Mark Wenig</FullName>
											</PartyName>
											<IndirectResourceContributorRole>Composer</IndirectResourceContributorRole>
										</IndirectResourceContributor>
								<IndirectResourceContributor>
										<PartyName>
											<FullName>Emily Elizabeth Dickinson</FullName>
										</PartyName>
										<IndirectResourceContributorRole>Lyricist</IndirectResourceContributorRole>
									</IndirectResourceContributor> 
							<LabelName>Poets of Rock</LabelName>
							<OriginalResourceReleaseDate>2025-04-10</OriginalResourceReleaseDate>
							<PLine>
							<Year>2025</Year>
							<PLineText>Mark Wenig</PLineText>
						 </PLine>
				        <Genre>
				          <GenreText>Rock</GenreText>
						  <SubGenre>None</SubGenre>
				        </Genre>
						<ParentalWarningType>NotExplicit</ParentalWarningType>
				        <TechnicalSoundRecordingDetails>
					          <TechnicalResourceDetailsReference>T3</TechnicalResourceDetailsReference>
					          <AudioCodecType UserDefinedValue='FLAC'>UserDefined</AudioCodecType>
					          <SamplingRate UnitOfMeasure='kHz'>44100</SamplingRate>
							  <BitsPerSample>16</BitsPerSample>
					          <IsPreview>false</IsPreview>
					          <File>
					            <FileName>5063740193321_003.flac</FileName>
					            <FilePath>resources/</FilePath>
								<HashSum>
					              <HashSum>47b19cba46e4a0ccc002c83e0e1bd0eb</HashSum>
					              <HashSumAlgorithmType>MD5</HashSumAlgorithmType>
								</HashSum>
					          </File>
					        </TechnicalSoundRecordingDetails></SoundRecordingDetailsByTerritory>
				    </SoundRecording><SoundRecording>
				      <SoundRecordingType>MusicalWorkSoundRecording</SoundRecordingType>
				      <SoundRecordingId>
				        <ISRC>GX38U2593826</ISRC>
				      </SoundRecordingId>
				      <ResourceReference>A4</ResourceReference>
				      <ReferenceTitle>
				        <TitleText>A Poison Tree</TitleText></ReferenceTitle>
				      <Duration>PT0H3M33S</Duration>
				      <SoundRecordingDetailsByTerritory>
				        <TerritoryCode>Worldwide</TerritoryCode><Title TitleType='FormalTitle'>
						  <TitleText>A Poison Tree</TitleText>
						</Title>
						<Title TitleType='DisplayTitle'>
						  <TitleText>A Poison Tree</TitleText>
						</Title><DisplayArtist>
							<PartyName>
							<FullName>Poets of Rock</FullName>
							</PartyName><ArtistRole>MainArtist</ArtistRole></DisplayArtist>
									<IndirectResourceContributor>
											<PartyName>
												<FullName>Mark Wenig</FullName>
											</PartyName>
											<IndirectResourceContributorRole>Composer</IndirectResourceContributorRole>
										</IndirectResourceContributor>
								<IndirectResourceContributor>
										<PartyName>
											<FullName>William Blake</FullName>
										</PartyName>
										<IndirectResourceContributorRole>Lyricist</IndirectResourceContributorRole>
									</IndirectResourceContributor> 
							<LabelName>Poets of Rock</LabelName>
							<OriginalResourceReleaseDate>2025-04-10</OriginalResourceReleaseDate>
							<PLine>
							<Year>2025</Year>
							<PLineText>Mark Wenig</PLineText>
						 </PLine>
				        <Genre>
				          <GenreText>Rock</GenreText>
						  <SubGenre>None</SubGenre>
				        </Genre>
						<ParentalWarningType>NotExplicit</ParentalWarningType>
				        <TechnicalSoundRecordingDetails>
					          <TechnicalResourceDetailsReference>T4</TechnicalResourceDetailsReference>
					          <AudioCodecType UserDefinedValue='FLAC'>UserDefined</AudioCodecType>
					          <SamplingRate UnitOfMeasure='kHz'>44100</SamplingRate>
							  <BitsPerSample>16</BitsPerSample>
					          <IsPreview>false</IsPreview>
					          <File>
					            <FileName>5063740193321_004.flac</FileName>
					            <FilePath>resources/</FilePath>
								<HashSum>
					              <HashSum>17969c417e21271d2058e83dfb8c254a</HashSum>
					              <HashSumAlgorithmType>MD5</HashSumAlgorithmType>
								</HashSum>
					          </File>
					        </TechnicalSoundRecordingDetails></SoundRecordingDetailsByTerritory>
				    </SoundRecording><SoundRecording>
				      <SoundRecordingType>MusicalWorkSoundRecording</SoundRecordingType>
				      <SoundRecordingId>
				        <ISRC>GX38U2589488</ISRC>
				      </SoundRecordingId>
				      <ResourceReference>A5</ResourceReference>
				      <ReferenceTitle>
				        <TitleText>Jabberwocky</TitleText></ReferenceTitle>
				      <Duration>PT0H3M57S</Duration>
				      <SoundRecordingDetailsByTerritory>
				        <TerritoryCode>Worldwide</TerritoryCode><Title TitleType='FormalTitle'>
						  <TitleText>Jabberwocky</TitleText>
						</Title>
						<Title TitleType='DisplayTitle'>
						  <TitleText>Jabberwocky</TitleText>
						</Title><DisplayArtist>
							<PartyName>
							<FullName>Poets of Rock</FullName>
							</PartyName><ArtistRole>MainArtist</ArtistRole></DisplayArtist>
									<IndirectResourceContributor>
											<PartyName>
												<FullName>Mark Wenig</FullName>
											</PartyName>
											<IndirectResourceContributorRole>Composer</IndirectResourceContributorRole>
										</IndirectResourceContributor>
								<IndirectResourceContributor>
										<PartyName>
											<FullName>Lewis Carroll</FullName>
										</PartyName>
										<IndirectResourceContributorRole>Lyricist</IndirectResourceContributorRole>
									</IndirectResourceContributor> 
							<LabelName>Poets of Rock</LabelName>
							<OriginalResourceReleaseDate>2025-04-10</OriginalResourceReleaseDate>
							<PLine>
							<Year>2025</Year>
							<PLineText>Mark Wenig</PLineText>
						 </PLine>
				        <Genre>
				          <GenreText>Rock</GenreText>
						  <SubGenre>None</SubGenre>
				        </Genre>
						<ParentalWarningType>NotExplicit</ParentalWarningType>
				        <TechnicalSoundRecordingDetails>
					          <TechnicalResourceDetailsReference>T5</TechnicalResourceDetailsReference>
					          <AudioCodecType UserDefinedValue='FLAC'>UserDefined</AudioCodecType>
					          <SamplingRate UnitOfMeasure='kHz'>44100</SamplingRate>
							  <BitsPerSample>16</BitsPerSample>
					          <IsPreview>false</IsPreview>
					          <File>
					            <FileName>5063740193321_005.flac</FileName>
					            <FilePath>resources/</FilePath>
								<HashSum>
					              <HashSum>91ebf711dc019c4dd4b26f8bf51ad674</HashSum>
					              <HashSumAlgorithmType>MD5</HashSumAlgorithmType>
								</HashSum>
					          </File>
					        </TechnicalSoundRecordingDetails></SoundRecordingDetailsByTerritory>
				    </SoundRecording><SoundRecording>
				      <SoundRecordingType>MusicalWorkSoundRecording</SoundRecordingType>
				      <SoundRecordingId>
				        <ISRC>GX38U2595819</ISRC>
				      </SoundRecordingId>
				      <ResourceReference>A6</ResourceReference>
				      <ReferenceTitle>
				        <TitleText>Shall I compare thee to a summer&#39;s day</TitleText></ReferenceTitle>
				      <Duration>PT0H3M45S</Duration>
				      <SoundRecordingDetailsByTerritory>
				        <TerritoryCode>Worldwide</TerritoryCode><Title TitleType='FormalTitle'>
						  <TitleText>Shall I compare thee to a summer&#39;s day</TitleText>
						</Title>
						<Title TitleType='DisplayTitle'>
						  <TitleText>Shall I compare thee to a summer&#39;s day</TitleText>
						</Title><DisplayArtist>
							<PartyName>
							<FullName>Poets of Rock</FullName>
							</PartyName><ArtistRole>MainArtist</ArtistRole></DisplayArtist>
									<IndirectResourceContributor>
											<PartyName>
												<FullName>Mark Wenig</FullName>
											</PartyName>
											<IndirectResourceContributorRole>Composer</IndirectResourceContributorRole>
										</IndirectResourceContributor>
								<IndirectResourceContributor>
										<PartyName>
											<FullName>William Shakespeare</FullName>
										</PartyName>
										<IndirectResourceContributorRole>Lyricist</IndirectResourceContributorRole>
									</IndirectResourceContributor> 
							<LabelName>Poets of Rock</LabelName>
							<OriginalResourceReleaseDate>2025-04-10</OriginalResourceReleaseDate>
							<PLine>
							<Year>2025</Year>
							<PLineText>Mark Wenig</PLineText>
						 </PLine>
				        <Genre>
				          <GenreText>Rock</GenreText>
						  <SubGenre>None</SubGenre>
				        </Genre>
						<ParentalWarningType>NotExplicit</ParentalWarningType>
				        <TechnicalSoundRecordingDetails>
					          <TechnicalResourceDetailsReference>T6</TechnicalResourceDetailsReference>
					          <AudioCodecType UserDefinedValue='FLAC'>UserDefined</AudioCodecType>
					          <SamplingRate UnitOfMeasure='kHz'>44100</SamplingRate>
							  <BitsPerSample>16</BitsPerSample>
					          <IsPreview>false</IsPreview>
					          <File>
					            <FileName>5063740193321_006.flac</FileName>
					            <FilePath>resources/</FilePath>
								<HashSum>
					              <HashSum>6e0bebeff948455f60573bdf78298d2c</HashSum>
					              <HashSumAlgorithmType>MD5</HashSumAlgorithmType>
								</HashSum>
					          </File>
					        </TechnicalSoundRecordingDetails></SoundRecordingDetailsByTerritory>
				    </SoundRecording><SoundRecording>
				      <SoundRecordingType>MusicalWorkSoundRecording</SoundRecordingType>
				      <SoundRecordingId>
				        <ISRC>GX38U2526416</ISRC>
				      </SoundRecordingId>
				      <ResourceReference>A7</ResourceReference>
				      <ReferenceTitle>
				        <TitleText>The Spider and the Fly</TitleText></ReferenceTitle>
				      <Duration>PT0H5M52S</Duration>
				      <SoundRecordingDetailsByTerritory>
				        <TerritoryCode>Worldwide</TerritoryCode><Title TitleType='FormalTitle'>
						  <TitleText>The Spider and the Fly</TitleText>
						</Title>
						<Title TitleType='DisplayTitle'>
						  <TitleText>The Spider and the Fly</TitleText>
						</Title><DisplayArtist>
							<PartyName>
							<FullName>Poets of Rock</FullName>
							</PartyName><ArtistRole>MainArtist</ArtistRole></DisplayArtist>
									<IndirectResourceContributor>
											<PartyName>
												<FullName>Mark Wenig</FullName>
											</PartyName>
											<IndirectResourceContributorRole>Composer</IndirectResourceContributorRole>
										</IndirectResourceContributor>
								<IndirectResourceContributor>
										<PartyName>
											<FullName>Mary Howitt</FullName>
										</PartyName>
										<IndirectResourceContributorRole>Lyricist</IndirectResourceContributorRole>
									</IndirectResourceContributor> 
							<LabelName>Poets of Rock</LabelName>
							<OriginalResourceReleaseDate>2025-04-10</OriginalResourceReleaseDate>
							<PLine>
							<Year>2025</Year>
							<PLineText>Mark Wenig</PLineText>
						 </PLine>
				        <Genre>
				          <GenreText>Rock</GenreText>
						  <SubGenre>None</SubGenre>
				        </Genre>
						<ParentalWarningType>NotExplicit</ParentalWarningType>
				        <TechnicalSoundRecordingDetails>
					          <TechnicalResourceDetailsReference>T7</TechnicalResourceDetailsReference>
					          <AudioCodecType UserDefinedValue='FLAC'>UserDefined</AudioCodecType>
					          <SamplingRate UnitOfMeasure='kHz'>44100</SamplingRate>
							  <BitsPerSample>16</BitsPerSample>
					          <IsPreview>false</IsPreview>
					          <File>
					            <FileName>5063740193321_007.flac</FileName>
					            <FilePath>resources/</FilePath>
								<HashSum>
					              <HashSum>8c0bbaf5a82a97e288e9491ffb3b8b68</HashSum>
					              <HashSumAlgorithmType>MD5</HashSumAlgorithmType>
								</HashSum>
					          </File>
					        </TechnicalSoundRecordingDetails></SoundRecordingDetailsByTerritory>
				    </SoundRecording><SoundRecording>
				      <SoundRecordingType>MusicalWorkSoundRecording</SoundRecordingType>
				      <SoundRecordingId>
				        <ISRC>GX38U2555726</ISRC>
				      </SoundRecordingId>
				      <ResourceReference>A8</ResourceReference>
				      <ReferenceTitle>
				        <TitleText>The Raven</TitleText></ReferenceTitle>
				      <Duration>PT0H9M08S</Duration>
				      <SoundRecordingDetailsByTerritory>
				        <TerritoryCode>Worldwide</TerritoryCode><Title TitleType='FormalTitle'>
						  <TitleText>The Raven</TitleText>
						</Title>
						<Title TitleType='DisplayTitle'>
						  <TitleText>The Raven</TitleText>
						</Title><DisplayArtist>
							<PartyName>
							<FullName>Poets of Rock</FullName>
							</PartyName><ArtistRole>MainArtist</ArtistRole></DisplayArtist>
									<IndirectResourceContributor>
											<PartyName>
												<FullName>Mark Wenig</FullName>
											</PartyName>
											<IndirectResourceContributorRole>Composer</IndirectResourceContributorRole>
										</IndirectResourceContributor>
								<IndirectResourceContributor>
										<PartyName>
											<FullName>Edgar Allan Poe</FullName>
										</PartyName>
										<IndirectResourceContributorRole>Lyricist</IndirectResourceContributorRole>
									</IndirectResourceContributor> 
							<LabelName>Poets of Rock</LabelName>
							<OriginalResourceReleaseDate>2025-04-10</OriginalResourceReleaseDate>
							<PLine>
							<Year>2025</Year>
							<PLineText>Mark Wenig</PLineText>
						 </PLine>
				        <Genre>
				          <GenreText>Rock</GenreText>
						  <SubGenre>None</SubGenre>
				        </Genre>
						<ParentalWarningType>NotExplicit</ParentalWarningType>
				        <TechnicalSoundRecordingDetails>
					          <TechnicalResourceDetailsReference>T8</TechnicalResourceDetailsReference>
					          <AudioCodecType UserDefinedValue='FLAC'>UserDefined</AudioCodecType>
					          <SamplingRate UnitOfMeasure='kHz'>44100</SamplingRate>
							  <BitsPerSample>16</BitsPerSample>
					          <IsPreview>false</IsPreview>
					          <File>
					            <FileName>5063740193321_008.flac</FileName>
					            <FilePath>resources/</FilePath>
								<HashSum>
					              <HashSum>36b89ca7b5c837fbf526ef1c189871b7</HashSum>
					              <HashSumAlgorithmType>MD5</HashSumAlgorithmType>
								</HashSum>
					          </File>
					        </TechnicalSoundRecordingDetails></SoundRecordingDetailsByTerritory>
				    </SoundRecording><SoundRecording>
				      <SoundRecordingType>MusicalWorkSoundRecording</SoundRecordingType>
				      <SoundRecordingId>
				        <ISRC>GX38U2587482</ISRC>
				      </SoundRecordingId>
				      <ResourceReference>A9</ResourceReference>
				      <ReferenceTitle>
				        <TitleText>Nevermore</TitleText></ReferenceTitle>
				      <Duration>PT0H5M48S</Duration>
				      <SoundRecordingDetailsByTerritory>
				        <TerritoryCode>Worldwide</TerritoryCode><Title TitleType='FormalTitle'>
						  <TitleText>Nevermore</TitleText>
						</Title>
						<Title TitleType='DisplayTitle'>
						  <TitleText>Nevermore</TitleText>
						</Title><DisplayArtist>
							<PartyName>
							<FullName>Poets of Rock</FullName>
							</PartyName><ArtistRole>MainArtist</ArtistRole></DisplayArtist>
									<IndirectResourceContributor>
											<PartyName>
												<FullName>Mark Wenig</FullName>
											</PartyName>
											<IndirectResourceContributorRole>Composer</IndirectResourceContributorRole>
										</IndirectResourceContributor>
								<IndirectResourceContributor>
										<PartyName>
											<FullName>Edgar Allan Poe</FullName>
										</PartyName>
										<IndirectResourceContributorRole>Lyricist</IndirectResourceContributorRole>
									</IndirectResourceContributor> 
							<LabelName>Poets of Rock</LabelName>
							<OriginalResourceReleaseDate>2025-04-10</OriginalResourceReleaseDate>
							<PLine>
							<Year>2025</Year>
							<PLineText>Mark Wenig</PLineText>
						 </PLine>
				        <Genre>
				          <GenreText>Rock</GenreText>
						  <SubGenre>None</SubGenre>
				        </Genre>
						<ParentalWarningType>NotExplicit</ParentalWarningType>
				        <TechnicalSoundRecordingDetails>
					          <TechnicalResourceDetailsReference>T9</TechnicalResourceDetailsReference>
					          <AudioCodecType UserDefinedValue='FLAC'>UserDefined</AudioCodecType>
					          <SamplingRate UnitOfMeasure='kHz'>44100</SamplingRate>
							  <BitsPerSample>16</BitsPerSample>
					          <IsPreview>false</IsPreview>
					          <File>
					            <FileName>5063740193321_009.flac</FileName>
					            <FilePath>resources/</FilePath>
								<HashSum>
					              <HashSum>cf45130e9f6b3d6a3a33182d5b1913c6</HashSum>
					              <HashSumAlgorithmType>MD5</HashSumAlgorithmType>
								</HashSum>
					          </File>
					        </TechnicalSoundRecordingDetails></SoundRecordingDetailsByTerritory>
				    </SoundRecording><SoundRecording>
				      <SoundRecordingType>MusicalWorkSoundRecording</SoundRecordingType>
				      <SoundRecordingId>
				        <ISRC>GX3HH2547210</ISRC>
				      </SoundRecordingId>
				      <ResourceReference>A10</ResourceReference>
				      <ReferenceTitle>
				        <TitleText>O Captain&#33; My Captain&#33;</TitleText></ReferenceTitle>
				      <Duration>PT0H2M48S</Duration>
				      <SoundRecordingDetailsByTerritory>
				        <TerritoryCode>Worldwide</TerritoryCode><Title TitleType='FormalTitle'>
						  <TitleText>O Captain&#33; My Captain&#33;</TitleText>
						</Title>
						<Title TitleType='DisplayTitle'>
						  <TitleText>O Captain&#33; My Captain&#33;</TitleText>
						</Title><DisplayArtist>
							<PartyName>
							<FullName>Poets of Rock</FullName>
							</PartyName><ArtistRole>MainArtist</ArtistRole></DisplayArtist>
									<IndirectResourceContributor>
											<PartyName>
												<FullName>Mark Wenig</FullName>
											</PartyName>
											<IndirectResourceContributorRole>Composer</IndirectResourceContributorRole>
										</IndirectResourceContributor>
								<IndirectResourceContributor>
										<PartyName>
											<FullName>Walt Whitman</FullName>
										</PartyName>
										<IndirectResourceContributorRole>Lyricist</IndirectResourceContributorRole>
									</IndirectResourceContributor> 
							<LabelName>Poets of Rock</LabelName>
							<OriginalResourceReleaseDate>2025-04-10</OriginalResourceReleaseDate>
							<PLine>
							<Year>2025</Year>
							<PLineText>Mark Wenig</PLineText>
						 </PLine>
				        <Genre>
				          <GenreText>Rock</GenreText>
						  <SubGenre>None</SubGenre>
				        </Genre>
						<ParentalWarningType>NotExplicit</ParentalWarningType>
				        <TechnicalSoundRecordingDetails>
					          <TechnicalResourceDetailsReference>T10</TechnicalResourceDetailsReference>
					          <AudioCodecType UserDefinedValue='FLAC'>UserDefined</AudioCodecType>
					          <SamplingRate UnitOfMeasure='kHz'>44100</SamplingRate>
							  <BitsPerSample>16</BitsPerSample>
					          <IsPreview>false</IsPreview>
					          <File>
					            <FileName>5063740193321_010.flac</FileName>
					            <FilePath>resources/</FilePath>
								<HashSum>
					              <HashSum>5214b4ae13a2d840684af439a14e0888</HashSum>
					              <HashSumAlgorithmType>MD5</HashSumAlgorithmType>
								</HashSum>
					          </File>
					        </TechnicalSoundRecordingDetails></SoundRecordingDetailsByTerritory>
				    </SoundRecording><SoundRecording>
				      <SoundRecordingType>MusicalWorkSoundRecording</SoundRecordingType>
				      <SoundRecordingId>
				        <ISRC>GX38U2572201</ISRC>
				      </SoundRecordingId>
				      <ResourceReference>A11</ResourceReference>
				      <ReferenceTitle>
				        <TitleText>If-</TitleText></ReferenceTitle>
				      <Duration>PT0H5M13S</Duration>
				      <SoundRecordingDetailsByTerritory>
				        <TerritoryCode>Worldwide</TerritoryCode><Title TitleType='FormalTitle'>
						  <TitleText>If-</TitleText>
						</Title>
						<Title TitleType='DisplayTitle'>
						  <TitleText>If-</TitleText>
						</Title><DisplayArtist>
							<PartyName>
							<FullName>Poets of Rock</FullName>
							</PartyName><ArtistRole>MainArtist</ArtistRole></DisplayArtist>
									<IndirectResourceContributor>
											<PartyName>
												<FullName>Mark Wenig</FullName>
											</PartyName>
											<IndirectResourceContributorRole>Composer</IndirectResourceContributorRole>
										</IndirectResourceContributor>
								<IndirectResourceContributor>
										<PartyName>
											<FullName>Rudyard Kipling</FullName>
										</PartyName>
										<IndirectResourceContributorRole>Lyricist</IndirectResourceContributorRole>
									</IndirectResourceContributor> 
							<LabelName>Poets of Rock</LabelName>
							<OriginalResourceReleaseDate>2025-04-10</OriginalResourceReleaseDate>
							<PLine>
							<Year>2025</Year>
							<PLineText>Mark Wenig</PLineText>
						 </PLine>
				        <Genre>
				          <GenreText>Rock</GenreText>
						  <SubGenre>None</SubGenre>
				        </Genre>
						<ParentalWarningType>NotExplicit</ParentalWarningType>
				        <TechnicalSoundRecordingDetails>
					          <TechnicalResourceDetailsReference>T11</TechnicalResourceDetailsReference>
					          <AudioCodecType UserDefinedValue='FLAC'>UserDefined</AudioCodecType>
					          <SamplingRate UnitOfMeasure='kHz'>44100</SamplingRate>
							  <BitsPerSample>16</BitsPerSample>
					          <IsPreview>false</IsPreview>
					          <File>
					            <FileName>5063740193321_011.flac</FileName>
					            <FilePath>resources/</FilePath>
								<HashSum>
					              <HashSum>ca484ac0686e38107a1a1b9b8ac383e4</HashSum>
					              <HashSumAlgorithmType>MD5</HashSumAlgorithmType>
								</HashSum>
					          </File>
					        </TechnicalSoundRecordingDetails></SoundRecordingDetailsByTerritory>
				    </SoundRecording><SoundRecording>
				      <SoundRecordingType>MusicalWorkSoundRecording</SoundRecordingType>
				      <SoundRecordingId>
				        <ISRC>GX38U2592607</ISRC>
				      </SoundRecordingId>
				      <ResourceReference>A12</ResourceReference>
				      <ReferenceTitle>
				        <TitleText>Erlkönig</TitleText></ReferenceTitle>
				      <Duration>PT0H4M20S</Duration>
				      <SoundRecordingDetailsByTerritory>
				        <TerritoryCode>Worldwide</TerritoryCode><Title TitleType='FormalTitle'>
						  <TitleText>Erlkönig</TitleText>
						</Title>
						<Title TitleType='DisplayTitle'>
						  <TitleText>Erlkönig</TitleText>
						</Title><DisplayArtist>
							<PartyName>
							<FullName>Poets of Rock</FullName>
							</PartyName><ArtistRole>MainArtist</ArtistRole></DisplayArtist>
									<IndirectResourceContributor>
											<PartyName>
												<FullName>Mark Wenig</FullName>
											</PartyName>
											<IndirectResourceContributorRole>Composer</IndirectResourceContributorRole>
										</IndirectResourceContributor>
								<IndirectResourceContributor>
										<PartyName>
											<FullName>Johann Wolfgang von Goethe</FullName>
										</PartyName>
										<IndirectResourceContributorRole>Lyricist</IndirectResourceContributorRole>
									</IndirectResourceContributor> 
							<LabelName>Poets of Rock</LabelName>
							<OriginalResourceReleaseDate>2025-04-10</OriginalResourceReleaseDate>
							<PLine>
							<Year>2025</Year>
							<PLineText>Mark Wenig</PLineText>
						 </PLine>
				        <Genre>
				          <GenreText>Rock</GenreText>
						  <SubGenre>None</SubGenre>
				        </Genre>
						<ParentalWarningType>NotExplicit</ParentalWarningType>
				        <TechnicalSoundRecordingDetails>
					          <TechnicalResourceDetailsReference>T12</TechnicalResourceDetailsReference>
					          <AudioCodecType UserDefinedValue='FLAC'>UserDefined</AudioCodecType>
					          <SamplingRate UnitOfMeasure='kHz'>44100</SamplingRate>
							  <BitsPerSample>16</BitsPerSample>
					          <IsPreview>false</IsPreview>
					          <File>
					            <FileName>5063740193321_012.flac</FileName>
					            <FilePath>resources/</FilePath>
								<HashSum>
					              <HashSum>a3edda219182347cbdb14dd3f700402d</HashSum>
					              <HashSumAlgorithmType>MD5</HashSumAlgorithmType>
								</HashSum>
					          </File>
					        </TechnicalSoundRecordingDetails></SoundRecordingDetailsByTerritory>
				    </SoundRecording><Image>
			      <ImageType>FrontCoverImage</ImageType>
			      <ImageId>
			        <ProprietaryId Namespace='CDB'>GGL_UIM_ID:[5063740193321.jpg]</ProprietaryId>
			      </ImageId>
			      <ResourceReference>A13</ResourceReference>
			      <ImageDetailsByTerritory>
			        <TerritoryCode>Worldwide</TerritoryCode><TechnicalImageDetails>
			          <TechnicalResourceDetailsReference>T1</TechnicalResourceDetailsReference>
			          <ImageCodecType>JPEG</ImageCodecType>
			          <ImageHeight>3000</ImageHeight>
			          <ImageWidth>3000</ImageWidth>
			          <File>
			            <FileName>5063740193321.jpg</FileName>
			            <FilePath>resources/</FilePath>
			            <HashSum>
			              <HashSum>a2a30f05278a80d6d6533802c8c13743</HashSum>
			              <HashSumAlgorithmType>MD5</HashSumAlgorithmType>
			            </HashSum>
			          </File>
					</TechnicalImageDetails></ImageDetailsByTerritory>
			    </Image></ResourceList><ReleaseList><Release>
		      <ReleaseId>
		        <ISRC>GX38U2569046</ISRC>
		      </ReleaseId>
		      <ReleaseReference>R1</ReleaseReference>
		      <ReferenceTitle>
		        <TitleText>One Day I Wrote Her Name Upon the Strand</TitleText></ReferenceTitle>
		      <ReleaseResourceReferenceList>
		        <ReleaseResourceReference ReleaseResourceType='PrimaryResource'>A1</ReleaseResourceReference>
		      </ReleaseResourceReferenceList>
		      <ReleaseType>TrackRelease</ReleaseType>
		      <ReleaseDetailsByTerritory>
		        <TerritoryCode>Worldwide</TerritoryCode>
		        <DisplayArtistName>Poets of Rock</DisplayArtistName>
		        <LabelName>Poets of Rock</LabelName><Title TitleType='FormalTitle'>
		          <TitleText>One Day I Wrote Her Name Upon the Strand</TitleText>
		        </Title>
		        <Title TitleType='DisplayTitle'>
		          <TitleText>One Day I Wrote Her Name Upon the Strand</TitleText>
		        </Title><DisplayArtist>
							<PartyName>
							<FullName>Poets of Rock</FullName>
							</PartyName><ArtistRole>MainArtist</ArtistRole></DisplayArtist>
					 <Genre>
		          <GenreText>Rock</GenreText>
				  <SubGenre>None</SubGenre>
		        </Genre>
		        <OriginalReleaseDate>2025-04-10</OriginalReleaseDate>
		      </ReleaseDetailsByTerritory>
			<PLine>
				<Year>2025</Year>
				<PLineText>Mark Wenig</PLineText>
			 </PLine>
			 <CLine>
				<Year>2025</Year>
				<CLineText>Mark Wenig</CLineText>
			</CLine>
			</Release>
		    <Release>
		      <ReleaseId>
		        <ISRC>GX38U2538353</ISRC>
		      </ReleaseId>
		      <ReleaseReference>R2</ReleaseReference>
		      <ReferenceTitle>
		        <TitleText>I Wandered Lonely as a Cloud</TitleText></ReferenceTitle>
		      <ReleaseResourceReferenceList>
		        <ReleaseResourceReference ReleaseResourceType='PrimaryResource'>A2</ReleaseResourceReference>
		      </ReleaseResourceReferenceList>
		      <ReleaseType>TrackRelease</ReleaseType>
		      <ReleaseDetailsByTerritory>
		        <TerritoryCode>Worldwide</TerritoryCode>
		        <DisplayArtistName>Poets of Rock</DisplayArtistName>
		        <LabelName>Poets of Rock</LabelName><Title TitleType='FormalTitle'>
		          <TitleText>I Wandered Lonely as a Cloud</TitleText>
		        </Title>
		        <Title TitleType='DisplayTitle'>
		          <TitleText>I Wandered Lonely as a Cloud</TitleText>
		        </Title><DisplayArtist>
							<PartyName>
							<FullName>Poets of Rock</FullName>
							</PartyName><ArtistRole>MainArtist</ArtistRole></DisplayArtist>
					 <Genre>
		          <GenreText>Rock</GenreText>
				  <SubGenre>None</SubGenre>
		        </Genre>
		        <OriginalReleaseDate>2025-04-10</OriginalReleaseDate>
		      </ReleaseDetailsByTerritory>
			<PLine>
				<Year>2025</Year>
				<PLineText>Mark Wenig</PLineText>
			 </PLine>
			 <CLine>
				<Year>2025</Year>
				<CLineText>Mark Wenig</CLineText>
			</CLine>
			</Release>
		    <Release>
		      <ReleaseId>
		        <ISRC>GX38U2501130</ISRC>
		      </ReleaseId>
		      <ReleaseReference>R3</ReleaseReference>
		      <ReferenceTitle>
		        <TitleText>Hope</TitleText></ReferenceTitle>
		      <ReleaseResourceReferenceList>
		        <ReleaseResourceReference ReleaseResourceType='PrimaryResource'>A3</ReleaseResourceReference>
		      </ReleaseResourceReferenceList>
		      <ReleaseType>TrackRelease</ReleaseType>
		      <ReleaseDetailsByTerritory>
		        <TerritoryCode>Worldwide</TerritoryCode>
		        <DisplayArtistName>Poets of Rock</DisplayArtistName>
		        <LabelName>Poets of Rock</LabelName><Title TitleType='FormalTitle'>
		          <TitleText>Hope</TitleText>
		        </Title>
		        <Title TitleType='DisplayTitle'>
		          <TitleText>Hope</TitleText>
		        </Title><DisplayArtist>
							<PartyName>
							<FullName>Poets of Rock</FullName>
							</PartyName><ArtistRole>MainArtist</ArtistRole></DisplayArtist>
					 <Genre>
		          <GenreText>Rock</GenreText>
				  <SubGenre>None</SubGenre>
		        </Genre>
		        <OriginalReleaseDate>2025-04-10</OriginalReleaseDate>
		      </ReleaseDetailsByTerritory>
			<PLine>
				<Year>2025</Year>
				<PLineText>Mark Wenig</PLineText>
			 </PLine>
			 <CLine>
				<Year>2025</Year>
				<CLineText>Mark Wenig</CLineText>
			</CLine>
			</Release>
		    <Release>
		      <ReleaseId>
		        <ISRC>GX38U2593826</ISRC>
		      </ReleaseId>
		      <ReleaseReference>R4</ReleaseReference>
		      <ReferenceTitle>
		        <TitleText>A Poison Tree</TitleText></ReferenceTitle>
		      <ReleaseResourceReferenceList>
		        <ReleaseResourceReference ReleaseResourceType='PrimaryResource'>A4</ReleaseResourceReference>
		      </ReleaseResourceReferenceList>
		      <ReleaseType>TrackRelease</ReleaseType>
		      <ReleaseDetailsByTerritory>
		        <TerritoryCode>Worldwide</TerritoryCode>
		        <DisplayArtistName>Poets of Rock</DisplayArtistName>
		        <LabelName>Poets of Rock</LabelName><Title TitleType='FormalTitle'>
		          <TitleText>A Poison Tree</TitleText>
		        </Title>
		        <Title TitleType='DisplayTitle'>
		          <TitleText>A Poison Tree</TitleText>
		        </Title><DisplayArtist>
							<PartyName>
							<FullName>Poets of Rock</FullName>
							</PartyName><ArtistRole>MainArtist</ArtistRole></DisplayArtist>
					 <Genre>
		          <GenreText>Rock</GenreText>
				  <SubGenre>None</SubGenre>
		        </Genre>
		        <OriginalReleaseDate>2025-04-10</OriginalReleaseDate>
		      </ReleaseDetailsByTerritory>
			<PLine>
				<Year>2025</Year>
				<PLineText>Mark Wenig</PLineText>
			 </PLine>
			 <CLine>
				<Year>2025</Year>
				<CLineText>Mark Wenig</CLineText>
			</CLine>
			</Release>
		    <Release>
		      <ReleaseId>
		        <ISRC>GX38U2589488</ISRC>
		      </ReleaseId>
		      <ReleaseReference>R5</ReleaseReference>
		      <ReferenceTitle>
		        <TitleText>Jabberwocky</TitleText></ReferenceTitle>
		      <ReleaseResourceReferenceList>
		        <ReleaseResourceReference ReleaseResourceType='PrimaryResource'>A5</ReleaseResourceReference>
		      </ReleaseResourceReferenceList>
		      <ReleaseType>TrackRelease</ReleaseType>
		      <ReleaseDetailsByTerritory>
		        <TerritoryCode>Worldwide</TerritoryCode>
		        <DisplayArtistName>Poets of Rock</DisplayArtistName>
		        <LabelName>Poets of Rock</LabelName><Title TitleType='FormalTitle'>
		          <TitleText>Jabberwocky</TitleText>
		        </Title>
		        <Title TitleType='DisplayTitle'>
		          <TitleText>Jabberwocky</TitleText>
		        </Title><DisplayArtist>
							<PartyName>
							<FullName>Poets of Rock</FullName>
							</PartyName><ArtistRole>MainArtist</ArtistRole></DisplayArtist>
					 <Genre>
		          <GenreText>Rock</GenreText>
				  <SubGenre>None</SubGenre>
		        </Genre>
		        <OriginalReleaseDate>2025-04-10</OriginalReleaseDate>
		      </ReleaseDetailsByTerritory>
			<PLine>
				<Year>2025</Year>
				<PLineText>Mark Wenig</PLineText>
			 </PLine>
			 <CLine>
				<Year>2025</Year>
				<CLineText>Mark Wenig</CLineText>
			</CLine>
			</Release>
		    <Release>
		      <ReleaseId>
		        <ISRC>GX38U2595819</ISRC>
		      </ReleaseId>
		      <ReleaseReference>R6</ReleaseReference>
		      <ReferenceTitle>
		        <TitleText>Shall I compare thee to a summer&#39;s day</TitleText></ReferenceTitle>
		      <ReleaseResourceReferenceList>
		        <ReleaseResourceReference ReleaseResourceType='PrimaryResource'>A6</ReleaseResourceReference>
		      </ReleaseResourceReferenceList>
		      <ReleaseType>TrackRelease</ReleaseType>
		      <ReleaseDetailsByTerritory>
		        <TerritoryCode>Worldwide</TerritoryCode>
		        <DisplayArtistName>Poets of Rock</DisplayArtistName>
		        <LabelName>Poets of Rock</LabelName><Title TitleType='FormalTitle'>
		          <TitleText>Shall I compare thee to a summer&#39;s day</TitleText>
		        </Title>
		        <Title TitleType='DisplayTitle'>
		          <TitleText>Shall I compare thee to a summer&#39;s day</TitleText>
		        </Title><DisplayArtist>
							<PartyName>
							<FullName>Poets of Rock</FullName>
							</PartyName><ArtistRole>MainArtist</ArtistRole></DisplayArtist>
					 <Genre>
		          <GenreText>Rock</GenreText>
				  <SubGenre>None</SubGenre>
		        </Genre>
		        <OriginalReleaseDate>2025-04-10</OriginalReleaseDate>
		      </ReleaseDetailsByTerritory>
			<PLine>
				<Year>2025</Year>
				<PLineText>Mark Wenig</PLineText>
			 </PLine>
			 <CLine>
				<Year>2025</Year>
				<CLineText>Mark Wenig</CLineText>
			</CLine>
			</Release>
		    <Release>
		      <ReleaseId>
		        <ISRC>GX38U2526416</ISRC>
		      </ReleaseId>
		      <ReleaseReference>R7</ReleaseReference>
		      <ReferenceTitle>
		        <TitleText>The Spider and the Fly</TitleText></ReferenceTitle>
		      <ReleaseResourceReferenceList>
		        <ReleaseResourceReference ReleaseResourceType='PrimaryResource'>A7</ReleaseResourceReference>
		      </ReleaseResourceReferenceList>
		      <ReleaseType>TrackRelease</ReleaseType>
		      <ReleaseDetailsByTerritory>
		        <TerritoryCode>Worldwide</TerritoryCode>
		        <DisplayArtistName>Poets of Rock</DisplayArtistName>
		        <LabelName>Poets of Rock</LabelName><Title TitleType='FormalTitle'>
		          <TitleText>The Spider and the Fly</TitleText>
		        </Title>
		        <Title TitleType='DisplayTitle'>
		          <TitleText>The Spider and the Fly</TitleText>
		        </Title><DisplayArtist>
							<PartyName>
							<FullName>Poets of Rock</FullName>
							</PartyName><ArtistRole>MainArtist</ArtistRole></DisplayArtist>
					 <Genre>
		          <GenreText>Rock</GenreText>
				  <SubGenre>None</SubGenre>
		        </Genre>
		        <OriginalReleaseDate>2025-04-10</OriginalReleaseDate>
		      </ReleaseDetailsByTerritory>
			<PLine>
				<Year>2025</Year>
				<PLineText>Mark Wenig</PLineText>
			 </PLine>
			 <CLine>
				<Year>2025</Year>
				<CLineText>Mark Wenig</CLineText>
			</CLine>
			</Release>
		    <Release>
		      <ReleaseId>
		        <ISRC>GX38U2555726</ISRC>
		      </ReleaseId>
		      <ReleaseReference>R8</ReleaseReference>
		      <ReferenceTitle>
		        <TitleText>The Raven</TitleText></ReferenceTitle>
		      <ReleaseResourceReferenceList>
		        <ReleaseResourceReference ReleaseResourceType='PrimaryResource'>A8</ReleaseResourceReference>
		      </ReleaseResourceReferenceList>
		      <ReleaseType>TrackRelease</ReleaseType>
		      <ReleaseDetailsByTerritory>
		        <TerritoryCode>Worldwide</TerritoryCode>
		        <DisplayArtistName>Poets of Rock</DisplayArtistName>
		        <LabelName>Poets of Rock</LabelName><Title TitleType='FormalTitle'>
		          <TitleText>The Raven</TitleText>
		        </Title>
		        <Title TitleType='DisplayTitle'>
		          <TitleText>The Raven</TitleText>
		        </Title><DisplayArtist>
							<PartyName>
							<FullName>Poets of Rock</FullName>
							</PartyName><ArtistRole>MainArtist</ArtistRole></DisplayArtist>
					 <Genre>
		          <GenreText>Rock</GenreText>
				  <SubGenre>None</SubGenre>
		        </Genre>
		        <OriginalReleaseDate>2025-04-10</OriginalReleaseDate>
		      </ReleaseDetailsByTerritory>
			<PLine>
				<Year>2025</Year>
				<PLineText>Mark Wenig</PLineText>
			 </PLine>
			 <CLine>
				<Year>2025</Year>
				<CLineText>Mark Wenig</CLineText>
			</CLine>
			</Release>
		    <Release>
		      <ReleaseId>
		        <ISRC>GX38U2587482</ISRC>
		      </ReleaseId>
		      <ReleaseReference>R9</ReleaseReference>
		      <ReferenceTitle>
		        <TitleText>Nevermore</TitleText></ReferenceTitle>
		      <ReleaseResourceReferenceList>
		        <ReleaseResourceReference ReleaseResourceType='PrimaryResource'>A9</ReleaseResourceReference>
		      </ReleaseResourceReferenceList>
		      <ReleaseType>TrackRelease</ReleaseType>
		      <ReleaseDetailsByTerritory>
		        <TerritoryCode>Worldwide</TerritoryCode>
		        <DisplayArtistName>Poets of Rock</DisplayArtistName>
		        <LabelName>Poets of Rock</LabelName><Title TitleType='FormalTitle'>
		          <TitleText>Nevermore</TitleText>
		        </Title>
		        <Title TitleType='DisplayTitle'>
		          <TitleText>Nevermore</TitleText>
		        </Title><DisplayArtist>
							<PartyName>
							<FullName>Poets of Rock</FullName>
							</PartyName><ArtistRole>MainArtist</ArtistRole></DisplayArtist>
					 <Genre>
		          <GenreText>Rock</GenreText>
				  <SubGenre>None</SubGenre>
		        </Genre>
		        <OriginalReleaseDate>2025-04-10</OriginalReleaseDate>
		      </ReleaseDetailsByTerritory>
			<PLine>
				<Year>2025</Year>
				<PLineText>Mark Wenig</PLineText>
			 </PLine>
			 <CLine>
				<Year>2025</Year>
				<CLineText>Mark Wenig</CLineText>
			</CLine>
			</Release>
		    <Release>
		      <ReleaseId>
		        <ISRC>GX3HH2547210</ISRC>
		      </ReleaseId>
		      <ReleaseReference>R10</ReleaseReference>
		      <ReferenceTitle>
		        <TitleText>O Captain&#33; My Captain&#33;</TitleText></ReferenceTitle>
		      <ReleaseResourceReferenceList>
		        <ReleaseResourceReference ReleaseResourceType='PrimaryResource'>A10</ReleaseResourceReference>
		      </ReleaseResourceReferenceList>
		      <ReleaseType>TrackRelease</ReleaseType>
		      <ReleaseDetailsByTerritory>
		        <TerritoryCode>Worldwide</TerritoryCode>
		        <DisplayArtistName>Poets of Rock</DisplayArtistName>
		        <LabelName>Poets of Rock</LabelName><Title TitleType='FormalTitle'>
		          <TitleText>O Captain&#33; My Captain&#33;</TitleText>
		        </Title>
		        <Title TitleType='DisplayTitle'>
		          <TitleText>O Captain&#33; My Captain&#33;</TitleText>
		        </Title><DisplayArtist>
							<PartyName>
							<FullName>Poets of Rock</FullName>
							</PartyName><ArtistRole>MainArtist</ArtistRole></DisplayArtist>
					 <Genre>
		          <GenreText>Rock</GenreText>
				  <SubGenre>None</SubGenre>
		        </Genre>
		        <OriginalReleaseDate>2025-04-10</OriginalReleaseDate>
		      </ReleaseDetailsByTerritory>
			<PLine>
				<Year>2025</Year>
				<PLineText>Mark Wenig</PLineText>
			 </PLine>
			 <CLine>
				<Year>2025</Year>
				<CLineText>Mark Wenig</CLineText>
			</CLine>
			</Release>
		    <Release>
		      <ReleaseId>
		        <ISRC>GX38U2572201</ISRC>
		      </ReleaseId>
		      <ReleaseReference>R11</ReleaseReference>
		      <ReferenceTitle>
		        <TitleText>If-</TitleText></ReferenceTitle>
		      <ReleaseResourceReferenceList>
		        <ReleaseResourceReference ReleaseResourceType='PrimaryResource'>A11</ReleaseResourceReference>
		      </ReleaseResourceReferenceList>
		      <ReleaseType>TrackRelease</ReleaseType>
		      <ReleaseDetailsByTerritory>
		        <TerritoryCode>Worldwide</TerritoryCode>
		        <DisplayArtistName>Poets of Rock</DisplayArtistName>
		        <LabelName>Poets of Rock</LabelName><Title TitleType='FormalTitle'>
		          <TitleText>If-</TitleText>
		        </Title>
		        <Title TitleType='DisplayTitle'>
		          <TitleText>If-</TitleText>
		        </Title><DisplayArtist>
							<PartyName>
							<FullName>Poets of Rock</FullName>
							</PartyName><ArtistRole>MainArtist</ArtistRole></DisplayArtist>
					 <Genre>
		          <GenreText>Rock</GenreText>
				  <SubGenre>None</SubGenre>
		        </Genre>
		        <OriginalReleaseDate>2025-04-10</OriginalReleaseDate>
		      </ReleaseDetailsByTerritory>
			<PLine>
				<Year>2025</Year>
				<PLineText>Mark Wenig</PLineText>
			 </PLine>
			 <CLine>
				<Year>2025</Year>
				<CLineText>Mark Wenig</CLineText>
			</CLine>
			</Release>
		    <Release>
		      <ReleaseId>
		        <ISRC>GX38U2592607</ISRC>
		      </ReleaseId>
		      <ReleaseReference>R12</ReleaseReference>
		      <ReferenceTitle>
		        <TitleText>Erlkönig</TitleText></ReferenceTitle>
		      <ReleaseResourceReferenceList>
		        <ReleaseResourceReference ReleaseResourceType='PrimaryResource'>A12</ReleaseResourceReference>
		      </ReleaseResourceReferenceList>
		      <ReleaseType>TrackRelease</ReleaseType>
		      <ReleaseDetailsByTerritory>
		        <TerritoryCode>Worldwide</TerritoryCode>
		        <DisplayArtistName>Poets of Rock</DisplayArtistName>
		        <LabelName>Poets of Rock</LabelName><Title TitleType='FormalTitle'>
		          <TitleText>Erlkönig</TitleText>
		        </Title>
		        <Title TitleType='DisplayTitle'>
		          <TitleText>Erlkönig</TitleText>
		        </Title><DisplayArtist>
							<PartyName>
							<FullName>Poets of Rock</FullName>
							</PartyName><ArtistRole>MainArtist</ArtistRole></DisplayArtist>
					 <Genre>
		          <GenreText>Rock</GenreText>
				  <SubGenre>None</SubGenre>
		        </Genre>
		        <OriginalReleaseDate>2025-04-10</OriginalReleaseDate>
		      </ReleaseDetailsByTerritory>
			<PLine>
				<Year>2025</Year>
				<PLineText>Mark Wenig</PLineText>
			 </PLine>
			 <CLine>
				<Year>2025</Year>
				<CLineText>Mark Wenig</CLineText>
			</CLine>
			</Release>
		    <Release IsMainRelease='true'>
		      <ReleaseId><ICPN IsEan='true'>5063740193321</ICPN><CatalogNumber Namespace='CDB'>PoetsofRock</CatalogNumber></ReleaseId><ReleaseReference>R0</ReleaseReference>
			<ReferenceTitle><TitleText>Poets of Rock</TitleText></ReferenceTitle><ReleaseResourceReferenceList>
			  <ReleaseResourceReference ReleaseResourceType='PrimaryResource'>A1</ReleaseResourceReference>
			  
			  <ReleaseResourceReference ReleaseResourceType='PrimaryResource'>A2</ReleaseResourceReference>
			  
			  <ReleaseResourceReference ReleaseResourceType='PrimaryResource'>A3</ReleaseResourceReference>
			  
			  <ReleaseResourceReference ReleaseResourceType='PrimaryResource'>A4</ReleaseResourceReference>
			  
			  <ReleaseResourceReference ReleaseResourceType='PrimaryResource'>A5</ReleaseResourceReference>
			  
			  <ReleaseResourceReference ReleaseResourceType='PrimaryResource'>A6</ReleaseResourceReference>
			  
			  <ReleaseResourceReference ReleaseResourceType='PrimaryResource'>A7</ReleaseResourceReference>
			  
			  <ReleaseResourceReference ReleaseResourceType='PrimaryResource'>A8</ReleaseResourceReference>
			  
			  <ReleaseResourceReference ReleaseResourceType='PrimaryResource'>A9</ReleaseResourceReference>
			  
			  <ReleaseResourceReference ReleaseResourceType='PrimaryResource'>A10</ReleaseResourceReference>
			  
			  <ReleaseResourceReference ReleaseResourceType='PrimaryResource'>A11</ReleaseResourceReference>
			  
			  <ReleaseResourceReference ReleaseResourceType='PrimaryResource'>A12</ReleaseResourceReference>
			    <ReleaseResourceReference ReleaseResourceType='SecondaryResource'>A13</ReleaseResourceReference></ReleaseResourceReferenceList><ReleaseType>Album</ReleaseType> <ReleaseDetailsByTerritory>
		        <TerritoryCode>Worldwide</TerritoryCode>
		        <DisplayArtistName>Poets of Rock</DisplayArtistName>
		        <LabelName>Poets of Rock</LabelName>
					<Title TitleType='FormalTitle'>
					  <TitleText>Poets of Rock</TitleText>
					</Title>
					<Title TitleType='DisplayTitle'>
					  <TitleText>Poets of Rock</TitleText>
					</Title><DisplayArtist>
							<PartyName>
							<FullName>Poets of Rock</FullName>
							</PartyName><ArtistRole>MainArtist</ArtistRole></DisplayArtist>
		        <ParentalWarningType>NotExplicit</ParentalWarningType>
				<ResourceGroup>
					<ResourceGroup>
						<Title TitleType='GroupingTitle'>
				          <TitleText>Poets of Rock</TitleText>
				  </Title><SequenceNumber>1</SequenceNumber><ResourceGroupContentItem>
				<SequenceNumber>1</SequenceNumber>
				<ResourceType>SoundRecording</ResourceType>
				<ReleaseResourceReference>A1</ReleaseResourceReference>
				</ResourceGroupContentItem><ResourceGroupContentItem>
				<SequenceNumber>2</SequenceNumber>
				<ResourceType>SoundRecording</ResourceType>
				<ReleaseResourceReference>A2</ReleaseResourceReference>
				</ResourceGroupContentItem><ResourceGroupContentItem>
				<SequenceNumber>3</SequenceNumber>
				<ResourceType>SoundRecording</ResourceType>
				<ReleaseResourceReference>A3</ReleaseResourceReference>
				</ResourceGroupContentItem><ResourceGroupContentItem>
				<SequenceNumber>4</SequenceNumber>
				<ResourceType>SoundRecording</ResourceType>
				<ReleaseResourceReference>A4</ReleaseResourceReference>
				</ResourceGroupContentItem><ResourceGroupContentItem>
				<SequenceNumber>5</SequenceNumber>
				<ResourceType>SoundRecording</ResourceType>
				<ReleaseResourceReference>A5</ReleaseResourceReference>
				</ResourceGroupContentItem><ResourceGroupContentItem>
				<SequenceNumber>6</SequenceNumber>
				<ResourceType>SoundRecording</ResourceType>
				<ReleaseResourceReference>A6</ReleaseResourceReference>
				</ResourceGroupContentItem><ResourceGroupContentItem>
				<SequenceNumber>7</SequenceNumber>
				<ResourceType>SoundRecording</ResourceType>
				<ReleaseResourceReference>A7</ReleaseResourceReference>
				</ResourceGroupContentItem><ResourceGroupContentItem>
				<SequenceNumber>8</SequenceNumber>
				<ResourceType>SoundRecording</ResourceType>
				<ReleaseResourceReference>A8</ReleaseResourceReference>
				</ResourceGroupContentItem><ResourceGroupContentItem>
				<SequenceNumber>9</SequenceNumber>
				<ResourceType>SoundRecording</ResourceType>
				<ReleaseResourceReference>A9</ReleaseResourceReference>
				</ResourceGroupContentItem><ResourceGroupContentItem>
				<SequenceNumber>10</SequenceNumber>
				<ResourceType>SoundRecording</ResourceType>
				<ReleaseResourceReference>A10</ReleaseResourceReference>
				</ResourceGroupContentItem><ResourceGroupContentItem>
				<SequenceNumber>11</SequenceNumber>
				<ResourceType>SoundRecording</ResourceType>
				<ReleaseResourceReference>A11</ReleaseResourceReference>
				</ResourceGroupContentItem><ResourceGroupContentItem>
				<SequenceNumber>12</SequenceNumber>
				<ResourceType>SoundRecording</ResourceType>
				<ReleaseResourceReference>A12</ReleaseResourceReference>
				</ResourceGroupContentItem> </ResourceGroup>
				  <ResourceGroupContentItem>
				 <ResourceType>Image</ResourceType>
				<ReleaseResourceReference>A13</ReleaseResourceReference>
				</ResourceGroupContentItem>
				</ResourceGroup>
		        <Genre>
		          <GenreText>Rock</GenreText>
				  <SubGenre>None</SubGenre>
		        </Genre>
		        <OriginalReleaseDate>2025-04-10</OriginalReleaseDate>
		      </ReleaseDetailsByTerritory>
			<PLine>
				<Year>2025</Year>
				<PLineText>Mark Wenig</PLineText>
			 </PLine>
			 <CLine>
				<Year>2025</Year>
				<CLineText>Mark Wenig</CLineText>
			</CLine>
		    </Release></ReleaseList>
		  <DealList>
		    <ReleaseDeal>
		      <DealReleaseReference>R0</DealReleaseReference>
               <Deal>
		        <DealTerms>
					<CommercialModelType>PayAsYouGoModel</CommercialModelType>
                    <CommercialModelType>AdvertisementSupportedModel</CommercialModelType>
                     <CommercialModelType>SubscriptionModel</CommercialModelType> 
		         <Usage> 
                     <UseType>PermanentDownload</UseType> 
                     <UseType>OnDemandStream</UseType> 
                      <UseType>NonInteractiveStream</UseType> 
                      <DistributionChannelType>InternetAndMobile</DistributionChannelType> 
                 </Usage> 
					<TerritoryCode>Worldwide</TerritoryCode>
					<ValidityPeriod><StartDateTime>2025-04-29T00:00:00</StartDateTime></ValidityPeriod>
		        </DealTerms>
			</Deal>
		    </ReleaseDeal>
			<ReleaseDeal>
		      <DealReleaseReference>R1</DealReleaseReference>
		      <Deal>
		        <DealTerms>
					<CommercialModelType>PayAsYouGoModel</CommercialModelType>
                    <CommercialModelType>AdvertisementSupportedModel</CommercialModelType>
                    <CommercialModelType>SubscriptionModel</CommercialModelType> 
					<Usage> 
						 <UseType>PermanentDownload</UseType> 
                          <UseType>OnDemandStream</UseType> 
                          <UseType>NonInteractiveStream</UseType> 
                          <DistributionChannelType>InternetAndMobile</DistributionChannelType> 
                      </Usage>
					<TerritoryCode>Worldwide</TerritoryCode>
					<ValidityPeriod><StartDateTime>2025-04-29T00:00:00</StartDateTime></ValidityPeriod>
		        </DealTerms>
			</Deal>				  		      
		    </ReleaseDeal>
			<ReleaseDeal>
		      <DealReleaseReference>R2</DealReleaseReference>
		      <Deal>
		        <DealTerms>
					<CommercialModelType>PayAsYouGoModel</CommercialModelType>
                    <CommercialModelType>AdvertisementSupportedModel</CommercialModelType>
                    <CommercialModelType>SubscriptionModel</CommercialModelType> 
					<Usage> 
						 <UseType>PermanentDownload</UseType> 
                          <UseType>OnDemandStream</UseType> 
                          <UseType>NonInteractiveStream</UseType> 
                          <DistributionChannelType>InternetAndMobile</DistributionChannelType> 
                      </Usage>
					<TerritoryCode>Worldwide</TerritoryCode>
					<ValidityPeriod><StartDateTime>2025-04-29T00:00:00</StartDateTime></ValidityPeriod>
		        </DealTerms>
			</Deal>				  		      
		    </ReleaseDeal>
			<ReleaseDeal>
		      <DealReleaseReference>R3</DealReleaseReference>
		      <Deal>
		        <DealTerms>
					<CommercialModelType>PayAsYouGoModel</CommercialModelType>
                    <CommercialModelType>AdvertisementSupportedModel</CommercialModelType>
                    <CommercialModelType>SubscriptionModel</CommercialModelType> 
					<Usage> 
						 <UseType>PermanentDownload</UseType> 
                          <UseType>OnDemandStream</UseType> 
                          <UseType>NonInteractiveStream</UseType> 
                          <DistributionChannelType>InternetAndMobile</DistributionChannelType> 
                      </Usage>
					<TerritoryCode>Worldwide</TerritoryCode>
					<ValidityPeriod><StartDateTime>2025-04-29T00:00:00</StartDateTime></ValidityPeriod>
		        </DealTerms>
			</Deal>				  		      
		    </ReleaseDeal>
			<ReleaseDeal>
		      <DealReleaseReference>R4</DealReleaseReference>
		      <Deal>
		        <DealTerms>
					<CommercialModelType>PayAsYouGoModel</CommercialModelType>
                    <CommercialModelType>AdvertisementSupportedModel</CommercialModelType>
                    <CommercialModelType>SubscriptionModel</CommercialModelType> 
					<Usage> 
						 <UseType>PermanentDownload</UseType> 
                          <UseType>OnDemandStream</UseType> 
                          <UseType>NonInteractiveStream</UseType> 
                          <DistributionChannelType>InternetAndMobile</DistributionChannelType> 
                      </Usage>
					<TerritoryCode>Worldwide</TerritoryCode>
					<ValidityPeriod><StartDateTime>2025-04-29T00:00:00</StartDateTime></ValidityPeriod>
		        </DealTerms>
			</Deal>				  		      
		    </ReleaseDeal>
			<ReleaseDeal>
		      <DealReleaseReference>R5</DealReleaseReference>
		      <Deal>
		        <DealTerms>
					<CommercialModelType>PayAsYouGoModel</CommercialModelType>
                    <CommercialModelType>AdvertisementSupportedModel</CommercialModelType>
                    <CommercialModelType>SubscriptionModel</CommercialModelType> 
					<Usage> 
						 <UseType>PermanentDownload</UseType> 
                          <UseType>OnDemandStream</UseType> 
                          <UseType>NonInteractiveStream</UseType> 
                          <DistributionChannelType>InternetAndMobile</DistributionChannelType> 
                      </Usage>
					<TerritoryCode>Worldwide</TerritoryCode>
					<ValidityPeriod><StartDateTime>2025-04-29T00:00:00</StartDateTime></ValidityPeriod>
		        </DealTerms>
			</Deal>				  		      
		    </ReleaseDeal>
			<ReleaseDeal>
		      <DealReleaseReference>R6</DealReleaseReference>
		      <Deal>
		        <DealTerms>
					<CommercialModelType>PayAsYouGoModel</CommercialModelType>
                    <CommercialModelType>AdvertisementSupportedModel</CommercialModelType>
                    <CommercialModelType>SubscriptionModel</CommercialModelType> 
					<Usage> 
						 <UseType>PermanentDownload</UseType> 
                          <UseType>OnDemandStream</UseType> 
                          <UseType>NonInteractiveStream</UseType> 
                          <DistributionChannelType>InternetAndMobile</DistributionChannelType> 
                      </Usage>
					<TerritoryCode>Worldwide</TerritoryCode>
					<ValidityPeriod><StartDateTime>2025-04-29T00:00:00</StartDateTime></ValidityPeriod>
		        </DealTerms>
			</Deal>				  		      
		    </ReleaseDeal>
			<ReleaseDeal>
		      <DealReleaseReference>R7</DealReleaseReference>
		      <Deal>
		        <DealTerms>
					<CommercialModelType>PayAsYouGoModel</CommercialModelType>
                    <CommercialModelType>AdvertisementSupportedModel</CommercialModelType>
                    <CommercialModelType>SubscriptionModel</CommercialModelType> 
					<Usage> 
						 <UseType>PermanentDownload</UseType> 
                          <UseType>OnDemandStream</UseType> 
                          <UseType>NonInteractiveStream</UseType> 
                          <DistributionChannelType>InternetAndMobile</DistributionChannelType> 
                      </Usage>
					<TerritoryCode>Worldwide</TerritoryCode>
					<ValidityPeriod><StartDateTime>2025-04-29T00:00:00</StartDateTime></ValidityPeriod>
		        </DealTerms>
			</Deal>				  		      
		    </ReleaseDeal>
			<ReleaseDeal>
		      <DealReleaseReference>R8</DealReleaseReference>
		      <Deal>
		        <DealTerms>
					<CommercialModelType>PayAsYouGoModel</CommercialModelType>
                    <CommercialModelType>AdvertisementSupportedModel</CommercialModelType>
                    <CommercialModelType>SubscriptionModel</CommercialModelType> 
					<Usage> 
						 <UseType>PermanentDownload</UseType> 
                          <UseType>OnDemandStream</UseType> 
                          <UseType>NonInteractiveStream</UseType> 
                          <DistributionChannelType>InternetAndMobile</DistributionChannelType> 
                      </Usage>
					<TerritoryCode>Worldwide</TerritoryCode>
					<ValidityPeriod><StartDateTime>2025-04-29T00:00:00</StartDateTime></ValidityPeriod>
		        </DealTerms>
			</Deal>				  		      
		    </ReleaseDeal>
			<ReleaseDeal>
		      <DealReleaseReference>R9</DealReleaseReference>
		      <Deal>
		        <DealTerms>
					<CommercialModelType>PayAsYouGoModel</CommercialModelType>
                    <CommercialModelType>AdvertisementSupportedModel</CommercialModelType>
                    <CommercialModelType>SubscriptionModel</CommercialModelType> 
					<Usage> 
						 <UseType>PermanentDownload</UseType> 
                          <UseType>OnDemandStream</UseType> 
                          <UseType>NonInteractiveStream</UseType> 
                          <DistributionChannelType>InternetAndMobile</DistributionChannelType> 
                      </Usage>
					<TerritoryCode>Worldwide</TerritoryCode>
					<ValidityPeriod><StartDateTime>2025-04-29T00:00:00</StartDateTime></ValidityPeriod>
		        </DealTerms>
			</Deal>				  		      
		    </ReleaseDeal>
			<ReleaseDeal>
		      <DealReleaseReference>R10</DealReleaseReference>
		      <Deal>
		        <DealTerms>
					<CommercialModelType>PayAsYouGoModel</CommercialModelType>
                    <CommercialModelType>AdvertisementSupportedModel</CommercialModelType>
                    <CommercialModelType>SubscriptionModel</CommercialModelType> 
					<Usage> 
						 <UseType>PermanentDownload</UseType> 
                          <UseType>OnDemandStream</UseType> 
                          <UseType>NonInteractiveStream</UseType> 
                          <DistributionChannelType>InternetAndMobile</DistributionChannelType> 
                      </Usage>
					<TerritoryCode>Worldwide</TerritoryCode>
					<ValidityPeriod><StartDateTime>2025-04-29T00:00:00</StartDateTime></ValidityPeriod>
		        </DealTerms>
			</Deal>				  		      
		    </ReleaseDeal>
			<ReleaseDeal>
		      <DealReleaseReference>R11</DealReleaseReference>
		      <Deal>
		        <DealTerms>
					<CommercialModelType>PayAsYouGoModel</CommercialModelType>
                    <CommercialModelType>AdvertisementSupportedModel</CommercialModelType>
                    <CommercialModelType>SubscriptionModel</CommercialModelType> 
					<Usage> 
						 <UseType>PermanentDownload</UseType> 
                          <UseType>OnDemandStream</UseType> 
                          <UseType>NonInteractiveStream</UseType> 
                          <DistributionChannelType>InternetAndMobile</DistributionChannelType> 
                      </Usage>
					<TerritoryCode>Worldwide</TerritoryCode>
					<ValidityPeriod><StartDateTime>2025-04-29T00:00:00</StartDateTime></ValidityPeriod>
		        </DealTerms>
			</Deal>				  		      
		    </ReleaseDeal>
			<ReleaseDeal>
		      <DealReleaseReference>R12</DealReleaseReference>
		      <Deal>
		        <DealTerms>
					<CommercialModelType>PayAsYouGoModel</CommercialModelType>
                    <CommercialModelType>AdvertisementSupportedModel</CommercialModelType>
                    <CommercialModelType>SubscriptionModel</CommercialModelType> 
					<Usage> 
						 <UseType>PermanentDownload</UseType> 
                          <UseType>OnDemandStream</UseType> 
                          <UseType>NonInteractiveStream</UseType> 
                          <DistributionChannelType>InternetAndMobile</DistributionChannelType> 
                      </Usage>
					<TerritoryCode>Worldwide</TerritoryCode>
					<ValidityPeriod><StartDateTime>2025-04-29T00:00:00</StartDateTime></ValidityPeriod>
		        </DealTerms>
			</Deal>				  		      
		    </ReleaseDeal>
			</DealList></ern:NewReleaseMessage>