<?xml version='1.0' encoding='UTF-8'?><ern:NewReleaseMessage xmlns:ern="http://ddex.net/xml/ern/382" xmlns:xs="http://www.w3.org/2001/XMLSchema-instance" xs:schemaLocation="http://ddex.net/xml/ern/382 http://ddex.net/xml/ern/382/release-notification.xsd" MessageSchemaVersionId="ern/382">
		<MessageHeader>
		    <MessageThreadId>723524</MessageThreadId>
		    <MessageId>F2991A5D031BBCD5EC652B753B33BFA9</MessageId>
		    <MessageSender>
		      <PartyId>PADPIDA2012091204O</PartyId>
		      <PartyName>
		        <FullName>Routenote</FullName>
		      </PartyName>
		    </MessageSender>
		    <MessageRecipient>
		      <PartyId>PADPIDA2011021513H</PartyId>
		      <PartyName>
		        <FullName>DEEZER</FullName>
		      </PartyName>
		    </MessageRecipient>
		    <MessageCreatedDateTime>2025-04-29T08:06:08Z</MessageCreatedDateTime>
		    <MessageControlType>LiveMessage</MessageControlType>
		  </MessageHeader><UpdateIndicator xmlns=''>OriginalMessage</UpdateIndicator><ResourceList><SoundRecording>
				      <SoundRecordingType>MusicalWorkSoundRecording</SoundRecordingType>
				      <SoundRecordingId>
				        <ISRC>GX3HH2514243</ISRC>
				      </SoundRecordingId>
				      <ResourceReference>A1</ResourceReference>
				      <ReferenceTitle>
				        <TitleText>Medley: Aesthetix / Gold / Chapter 2</TitleText></ReferenceTitle>
				      <Duration>PT0H6M43S</Duration>
				      <SoundRecordingDetailsByTerritory>
				        <TerritoryCode>Worldwide</TerritoryCode><Title TitleType='FormalTitle'>
						  <TitleText>Medley: Aesthetix / Gold / Chapter 2</TitleText>
						</Title>
						<Title TitleType='DisplayTitle'>
						  <TitleText>Medley: Aesthetix / Gold / Chapter 2</TitleText>
						</Title><DisplayArtist>
							<PartyName>
							<FullName>FoxMPlayz</FullName>
							</PartyName><ArtistRole>MainArtist</ArtistRole></DisplayArtist>
									<IndirectResourceContributor>
											<PartyName>
												<FullName>Fox McCloud</FullName>
											</PartyName>
											<IndirectResourceContributorRole>Composer</IndirectResourceContributorRole>
										</IndirectResourceContributor>
								<IndirectResourceContributor>
										<PartyName>
											<FullName>Fox McCloud</FullName>
										</PartyName>
										<IndirectResourceContributorRole>Lyricist</IndirectResourceContributorRole>
									</IndirectResourceContributor> 
							<LabelName>FoxMPlayz</LabelName>
							<OriginalResourceReleaseDate>2025-04-09</OriginalResourceReleaseDate>
							<PLine>
							<Year>2025</Year>
							<PLineText>FoxMPlayz</PLineText>
						 </PLine>
				        <Genre>
				          <GenreText>Electronic</GenreText>
						  <SubGenre>None</SubGenre>
				        </Genre>
						<ParentalWarningType>NotExplicit</ParentalWarningType>
				        <TechnicalSoundRecordingDetails>
					          <TechnicalResourceDetailsReference>T1</TechnicalResourceDetailsReference>
					          <AudioCodecType UserDefinedValue='FLAC'>UserDefined</AudioCodecType>
					          <SamplingRate UnitOfMeasure='kHz'>44100</SamplingRate>
							  <BitsPerSample>16</BitsPerSample>
					          <IsPreview>false</IsPreview>
					          <File>
					            <FileName>5063740178434_001.flac</FileName>
					            <FilePath>resources/</FilePath>
								<HashSum>
					              <HashSum>b3f88e64e86c39a794515ed98b270307</HashSum>
					              <HashSumAlgorithmType>MD5</HashSumAlgorithmType>
								</HashSum>
					          </File>
					        </TechnicalSoundRecordingDetails></SoundRecordingDetailsByTerritory>
				    </SoundRecording><Image>
			      <ImageType>FrontCoverImage</ImageType>
			      <ImageId>
			        <ProprietaryId Namespace='CDB'>GGL_UIM_ID:[5063740178434.jpg]</ProprietaryId>
			      </ImageId>
			      <ResourceReference>A2</ResourceReference>
			      <ImageDetailsByTerritory>
			        <TerritoryCode>Worldwide</TerritoryCode><TechnicalImageDetails>
			          <TechnicalResourceDetailsReference>T1</TechnicalResourceDetailsReference>
			          <ImageCodecType>JPEG</ImageCodecType>
			          <ImageHeight>3000</ImageHeight>
			          <ImageWidth>3000</ImageWidth>
			          <File>
			            <FileName>5063740178434.jpg</FileName>
			            <FilePath>resources/</FilePath>
			            <HashSum>
			              <HashSum>063f7b2960384d9ba97779c350fbaa9e</HashSum>
			              <HashSumAlgorithmType>MD5</HashSumAlgorithmType>
			            </HashSum>
			          </File>
					</TechnicalImageDetails></ImageDetailsByTerritory>
			    </Image></ResourceList><ReleaseList><Release>
		      <ReleaseId>
		        <ISRC>GX3HH2514243</ISRC>
		      </ReleaseId>
		      <ReleaseReference>R1</ReleaseReference>
		      <ReferenceTitle>
		        <TitleText>Medley: Aesthetix / Gold / Chapter 2</TitleText></ReferenceTitle>
		      <ReleaseResourceReferenceList>
		        <ReleaseResourceReference ReleaseResourceType='PrimaryResource'>A1</ReleaseResourceReference>
		      </ReleaseResourceReferenceList>
		      <ReleaseType>TrackRelease</ReleaseType>
		      <ReleaseDetailsByTerritory>
		        <TerritoryCode>Worldwide</TerritoryCode>
		        <DisplayArtistName>FoxMPlayz</DisplayArtistName>
		        <LabelName>FoxMPlayz</LabelName><Title TitleType='FormalTitle'>
		          <TitleText>Medley: Aesthetix / Gold / Chapter 2</TitleText>
		        </Title>
		        <Title TitleType='DisplayTitle'>
		          <TitleText>Medley: Aesthetix / Gold / Chapter 2</TitleText>
		        </Title><DisplayArtist>
							<PartyName>
							<FullName>FoxMPlayz</FullName>
							</PartyName><ArtistRole>MainArtist</ArtistRole></DisplayArtist>
					 <Genre>
		          <GenreText>Electronic</GenreText>
				  <SubGenre>None</SubGenre>
		        </Genre>
		        <OriginalReleaseDate>2025-04-09</OriginalReleaseDate>
		      </ReleaseDetailsByTerritory>
			<PLine>
				<Year>2025</Year>
				<PLineText>FoxMPlayz</PLineText>
			 </PLine>
			 <CLine>
				<Year>2025</Year>
				<CLineText>FoxMPlayz</CLineText>
			</CLine>
			</Release>
		    <Release IsMainRelease='true'>
		      <ReleaseId><ICPN IsEan='true'>5063740178434</ICPN><CatalogNumber Namespace='CDB'>FoxMPlayz</CatalogNumber></ReleaseId><ReleaseReference>R0</ReleaseReference>
			<ReferenceTitle><TitleText>Medley: Aesthetix / Gold / Chapter 2</TitleText></ReferenceTitle><ReleaseResourceReferenceList>
			  <ReleaseResourceReference ReleaseResourceType='PrimaryResource'>A1</ReleaseResourceReference>
			    <ReleaseResourceReference ReleaseResourceType='SecondaryResource'>A2</ReleaseResourceReference></ReleaseResourceReferenceList><ReleaseType>Single</ReleaseType> <ReleaseDetailsByTerritory>
		        <TerritoryCode>Worldwide</TerritoryCode>
		        <DisplayArtistName>FoxMPlayz</DisplayArtistName>
		        <LabelName>FoxMPlayz</LabelName>
					<Title TitleType='FormalTitle'>
					  <TitleText>Medley: Aesthetix / Gold / Chapter 2</TitleText>
					</Title>
					<Title TitleType='DisplayTitle'>
					  <TitleText>Medley: Aesthetix / Gold / Chapter 2</TitleText>
					</Title><DisplayArtist>
							<PartyName>
							<FullName>FoxMPlayz</FullName>
							</PartyName><ArtistRole>MainArtist</ArtistRole></DisplayArtist>
		        <ParentalWarningType>NotExplicit</ParentalWarningType>
				<ResourceGroup>
					<ResourceGroup>
						<Title TitleType='GroupingTitle'>
				          <TitleText>Medley: Aesthetix / Gold / Chapter 2</TitleText>
				  </Title><SequenceNumber>1</SequenceNumber><ResourceGroupContentItem>
				<SequenceNumber>1</SequenceNumber>
				<ResourceType>SoundRecording</ResourceType>
				<ReleaseResourceReference>A1</ReleaseResourceReference>
				</ResourceGroupContentItem> </ResourceGroup>
				  <ResourceGroupContentItem>
				 <ResourceType>Image</ResourceType>
				<ReleaseResourceReference>A2</ReleaseResourceReference>
				</ResourceGroupContentItem>
				</ResourceGroup>
		        <Genre>
		          <GenreText>Electronic</GenreText>
				  <SubGenre>None</SubGenre>
		        </Genre>
		        <OriginalReleaseDate>2025-04-09</OriginalReleaseDate>
		      </ReleaseDetailsByTerritory>
			<PLine>
				<Year>2025</Year>
				<PLineText>FoxMPlayz</PLineText>
			 </PLine>
			 <CLine>
				<Year>2025</Year>
				<CLineText>FoxMPlayz</CLineText>
			</CLine>
		    </Release></ReleaseList>
		  <DealList>
		    <ReleaseDeal>
		      <DealReleaseReference>R0</DealReleaseReference>
               <Deal>
		        <DealTerms>
					<CommercialModelType>PayAsYouGoModel</CommercialModelType>
                    <CommercialModelType>AdvertisementSupportedModel</CommercialModelType>
                     <CommercialModelType>SubscriptionModel</CommercialModelType> 
		         <Usage> 
                     <UseType>PermanentDownload</UseType> 
                     <UseType>OnDemandStream</UseType> 
                      <UseType>NonInteractiveStream</UseType> 
                      <DistributionChannelType>InternetAndMobile</DistributionChannelType> 
                 </Usage> 
					<TerritoryCode>Worldwide</TerritoryCode>
					<ValidityPeriod><StartDateTime>2025-04-23T00:00:00</StartDateTime></ValidityPeriod>
		        </DealTerms>
			</Deal>
		    </ReleaseDeal>
			<ReleaseDeal>
		      <DealReleaseReference>R1</DealReleaseReference>
		      <Deal>
		        <DealTerms>
					<CommercialModelType>PayAsYouGoModel</CommercialModelType>
                    <CommercialModelType>AdvertisementSupportedModel</CommercialModelType>
                    <CommercialModelType>SubscriptionModel</CommercialModelType> 
					<Usage> 
						 <UseType>PermanentDownload</UseType> 
                          <UseType>OnDemandStream</UseType> 
                          <UseType>NonInteractiveStream</UseType> 
                          <DistributionChannelType>InternetAndMobile</DistributionChannelType> 
                      </Usage>
					<TerritoryCode>Worldwide</TerritoryCode>
					<ValidityPeriod><StartDateTime>2025-04-23T00:00:00</StartDateTime></ValidityPeriod>
		        </DealTerms>
			</Deal>				  		      
		    </ReleaseDeal>
			</DealList></ern:NewReleaseMessage>