<?xml version='1.0' encoding='UTF-8'?><ern:NewReleaseMessage xmlns:ern="http://ddex.net/xml/ern/382" xmlns:xs="http://www.w3.org/2001/XMLSchema-instance" xs:schemaLocation="http://ddex.net/xml/ern/382 http://ddex.net/xml/ern/382/release-notification.xsd" MessageSchemaVersionId="ern/382">
		<MessageHeader>
		    <MessageThreadId>723524</MessageThreadId>
		    <MessageId>0E2CAF3E1C80A45ADDD07020A3983BEC</MessageId>
		    <MessageSender>
		      <PartyId>PADPIDA2012091204O</PartyId>
		      <PartyName>
		        <FullName>Routenote</FullName>
		      </PartyName>
		    </MessageSender>
		    <MessageRecipient>
		      <PartyId>PADPIDA2011021513H</PartyId>
		      <PartyName>
		        <FullName>DEEZER</FullName>
		      </PartyName>
		    </MessageRecipient>
		    <MessageCreatedDateTime>2025-04-29T08:11:54Z</MessageCreatedDateTime>
		    <MessageControlType>LiveMessage</MessageControlType>
		  </MessageHeader><UpdateIndicator xmlns=''>OriginalMessage</UpdateIndicator><ResourceList><SoundRecording>
				      <SoundRecordingType>MusicalWorkSoundRecording</SoundRecordingType>
				      <SoundRecordingId>
				        <ISRC>GX8KD2583057</ISRC>
				      </SoundRecordingId>
				      <ResourceReference>A1</ResourceReference>
				      <ReferenceTitle>
				        <TitleText>dac ma bič</TitleText></ReferenceTitle>
				      <Duration>PT0H3M09S</Duration>
				      <SoundRecordingDetailsByTerritory>
				        <TerritoryCode>Worldwide</TerritoryCode><Title TitleType='FormalTitle'>
						  <TitleText>dac ma bič</TitleText>
						</Title>
						<Title TitleType='DisplayTitle'>
						  <TitleText>dac ma bič</TitleText>
						</Title><DisplayArtist>
							<PartyName>
							<FullName>kichmee</FullName>
							</PartyName><ArtistRole>MainArtist</ArtistRole></DisplayArtist><DisplayArtist>
							<PartyName>
							<FullName>Kontrabandz</FullName>
							</PartyName><ArtistRole>Producer</ArtistRole></DisplayArtist>
									<IndirectResourceContributor>
											<PartyName>
												<FullName>kichmee kichmee</FullName>
											</PartyName>
											<IndirectResourceContributorRole>Composer</IndirectResourceContributorRole>
										</IndirectResourceContributor>
								<IndirectResourceContributor>
										<PartyName>
											<FullName>kichmee kichmee</FullName>
										</PartyName>
										<IndirectResourceContributorRole>Lyricist</IndirectResourceContributorRole>
									</IndirectResourceContributor> 
							<LabelName>AK1MBO</LabelName>
							<OriginalResourceReleaseDate>2025-01-29</OriginalResourceReleaseDate>
							<PLine>
							<Year>2025</Year>
							<PLineText>AK1MBO</PLineText>
						 </PLine>
				        <Genre>
				          <GenreText>Hip Hop/Rap</GenreText>
						  <SubGenre>None</SubGenre>
				        </Genre>
						<ParentalWarningType>Explicit</ParentalWarningType>
				        <TechnicalSoundRecordingDetails>
					          <TechnicalResourceDetailsReference>T1</TechnicalResourceDetailsReference>
					          <AudioCodecType UserDefinedValue='FLAC'>UserDefined</AudioCodecType>
					          <SamplingRate UnitOfMeasure='kHz'>44100</SamplingRate>
							  <BitsPerSample>16</BitsPerSample>
					          <IsPreview>false</IsPreview>
					          <File>
					            <FileName>5063687600036_001.flac</FileName>
					            <FilePath>resources/</FilePath>
								<HashSum>
					              <HashSum>153bf6eb53977e29e2055256db065ddc</HashSum>
					              <HashSumAlgorithmType>MD5</HashSumAlgorithmType>
								</HashSum>
					          </File>
					        </TechnicalSoundRecordingDetails></SoundRecordingDetailsByTerritory>
				    </SoundRecording><SoundRecording>
				      <SoundRecordingType>MusicalWorkSoundRecording</SoundRecordingType>
				      <SoundRecordingId>
				        <ISRC>GX8KD2533338</ISRC>
				      </SoundRecordingId>
				      <ResourceReference>A2</ResourceReference>
				      <ReferenceTitle>
				        <TitleText>all nighter</TitleText></ReferenceTitle>
				      <Duration>PT0H2M26S</Duration>
				      <SoundRecordingDetailsByTerritory>
				        <TerritoryCode>Worldwide</TerritoryCode><Title TitleType='FormalTitle'>
						  <TitleText>all nighter</TitleText>
						</Title>
						<Title TitleType='DisplayTitle'>
						  <TitleText>all nighter</TitleText>
						</Title><DisplayArtist>
							<PartyName>
							<FullName>kichmee</FullName>
							</PartyName><ArtistRole>MainArtist</ArtistRole></DisplayArtist><DisplayArtist>
							<PartyName>
							<FullName>kichmee</FullName>
							</PartyName><ArtistRole>Producer</ArtistRole></DisplayArtist>
									<IndirectResourceContributor>
											<PartyName>
												<FullName>kichmee kichmee</FullName>
											</PartyName>
											<IndirectResourceContributorRole>Composer</IndirectResourceContributorRole>
										</IndirectResourceContributor>
								<IndirectResourceContributor>
										<PartyName>
											<FullName>kichmee kichmee</FullName>
										</PartyName>
										<IndirectResourceContributorRole>Lyricist</IndirectResourceContributorRole>
									</IndirectResourceContributor> 
							<LabelName>AK1MBO</LabelName>
							<OriginalResourceReleaseDate>2025-01-29</OriginalResourceReleaseDate>
							<PLine>
							<Year>2025</Year>
							<PLineText>AK1MBO</PLineText>
						 </PLine>
				        <Genre>
				          <GenreText>Hip Hop/Rap</GenreText>
						  <SubGenre>None</SubGenre>
				        </Genre>
						<ParentalWarningType>Explicit</ParentalWarningType>
				        <TechnicalSoundRecordingDetails>
					          <TechnicalResourceDetailsReference>T2</TechnicalResourceDetailsReference>
					          <AudioCodecType UserDefinedValue='FLAC'>UserDefined</AudioCodecType>
					          <SamplingRate UnitOfMeasure='kHz'>44100</SamplingRate>
							  <BitsPerSample>16</BitsPerSample>
					          <IsPreview>false</IsPreview>
					          <File>
					            <FileName>5063687600036_002.flac</FileName>
					            <FilePath>resources/</FilePath>
								<HashSum>
					              <HashSum>304547737fde7b2cccfeac0fe270be5f</HashSum>
					              <HashSumAlgorithmType>MD5</HashSumAlgorithmType>
								</HashSum>
					          </File>
					        </TechnicalSoundRecordingDetails></SoundRecordingDetailsByTerritory>
				    </SoundRecording><SoundRecording>
				      <SoundRecordingType>MusicalWorkSoundRecording</SoundRecordingType>
				      <SoundRecordingId>
				        <ISRC>GX8KD2510277</ISRC>
				      </SoundRecordingId>
				      <ResourceReference>A3</ResourceReference>
				      <ReferenceTitle>
				        <TitleText>fan</TitleText></ReferenceTitle>
				      <Duration>PT0H2M32S</Duration>
				      <SoundRecordingDetailsByTerritory>
				        <TerritoryCode>Worldwide</TerritoryCode><Title TitleType='FormalTitle'>
						  <TitleText>fan</TitleText>
						</Title>
						<Title TitleType='DisplayTitle'>
						  <TitleText>fan</TitleText>
						</Title><DisplayArtist>
							<PartyName>
							<FullName>kichmee</FullName>
							</PartyName><ArtistRole>MainArtist</ArtistRole></DisplayArtist><DisplayArtist>
							<PartyName>
							<FullName>jannychan</FullName>
							</PartyName><ArtistRole>Producer</ArtistRole></DisplayArtist>
									<IndirectResourceContributor>
											<PartyName>
												<FullName>kichmee kichmee</FullName>
											</PartyName>
											<IndirectResourceContributorRole>Composer</IndirectResourceContributorRole>
										</IndirectResourceContributor>
								<IndirectResourceContributor>
										<PartyName>
											<FullName>kichmee kichmee</FullName>
										</PartyName>
										<IndirectResourceContributorRole>Lyricist</IndirectResourceContributorRole>
									</IndirectResourceContributor> 
							<LabelName>AK1MBO</LabelName>
							<OriginalResourceReleaseDate>2025-01-29</OriginalResourceReleaseDate>
							<PLine>
							<Year>2025</Year>
							<PLineText>AK1MBO</PLineText>
						 </PLine>
				        <Genre>
				          <GenreText>Hip Hop/Rap</GenreText>
						  <SubGenre>None</SubGenre>
				        </Genre>
						<ParentalWarningType>Explicit</ParentalWarningType>
				        <TechnicalSoundRecordingDetails>
					          <TechnicalResourceDetailsReference>T3</TechnicalResourceDetailsReference>
					          <AudioCodecType UserDefinedValue='FLAC'>UserDefined</AudioCodecType>
					          <SamplingRate UnitOfMeasure='kHz'>44100</SamplingRate>
							  <BitsPerSample>16</BitsPerSample>
					          <IsPreview>false</IsPreview>
					          <File>
					            <FileName>5063687600036_003.flac</FileName>
					            <FilePath>resources/</FilePath>
								<HashSum>
					              <HashSum>1986d3c2027250eaa85a7ef92f4974e0</HashSum>
					              <HashSumAlgorithmType>MD5</HashSumAlgorithmType>
								</HashSum>
					          </File>
					        </TechnicalSoundRecordingDetails></SoundRecordingDetailsByTerritory>
				    </SoundRecording><Image>
			      <ImageType>FrontCoverImage</ImageType>
			      <ImageId>
			        <ProprietaryId Namespace='CDB'>GGL_UIM_ID:[5063687600036.jpg]</ProprietaryId>
			      </ImageId>
			      <ResourceReference>A4</ResourceReference>
			      <ImageDetailsByTerritory>
			        <TerritoryCode>Worldwide</TerritoryCode><TechnicalImageDetails>
			          <TechnicalResourceDetailsReference>T1</TechnicalResourceDetailsReference>
			          <ImageCodecType>JPEG</ImageCodecType>
			          <ImageHeight>3000</ImageHeight>
			          <ImageWidth>3000</ImageWidth>
			          <File>
			            <FileName>5063687600036.jpg</FileName>
			            <FilePath>resources/</FilePath>
			            <HashSum>
			              <HashSum>2ae3394a9fe777d21a2386eb09cf573a</HashSum>
			              <HashSumAlgorithmType>MD5</HashSumAlgorithmType>
			            </HashSum>
			          </File>
					</TechnicalImageDetails></ImageDetailsByTerritory>
			    </Image></ResourceList><ReleaseList><Release>
		      <ReleaseId>
		        <ISRC>GX8KD2583057</ISRC>
		      </ReleaseId>
		      <ReleaseReference>R1</ReleaseReference>
		      <ReferenceTitle>
		        <TitleText>dac ma bič</TitleText></ReferenceTitle>
		      <ReleaseResourceReferenceList>
		        <ReleaseResourceReference ReleaseResourceType='PrimaryResource'>A1</ReleaseResourceReference>
		      </ReleaseResourceReferenceList>
		      <ReleaseType>TrackRelease</ReleaseType>
		      <ReleaseDetailsByTerritory>
		        <TerritoryCode>Worldwide</TerritoryCode>
		        <DisplayArtistName>kichmee</DisplayArtistName>
		        <LabelName>AK1MBO</LabelName><Title TitleType='FormalTitle'>
		          <TitleText>dac ma bič</TitleText>
		        </Title>
		        <Title TitleType='DisplayTitle'>
		          <TitleText>dac ma bič</TitleText>
		        </Title><DisplayArtist>
							<PartyName>
							<FullName>kichmee</FullName>
							</PartyName><ArtistRole>MainArtist</ArtistRole></DisplayArtist><DisplayArtist>
							<PartyName>
							<FullName>Kontrabandz</FullName>
							</PartyName><ArtistRole>Producer</ArtistRole></DisplayArtist>
					 <Genre>
		          <GenreText>Hip Hop/Rap</GenreText>
				  <SubGenre>None</SubGenre>
		        </Genre>
		        <OriginalReleaseDate>2025-01-29</OriginalReleaseDate>
		      </ReleaseDetailsByTerritory>
			<PLine>
				<Year>2025</Year>
				<PLineText>AK1MBO</PLineText>
			 </PLine>
			 <CLine>
				<Year>2025</Year>
				<CLineText>AK1MBO</CLineText>
			</CLine>
			</Release>
		    <Release>
		      <ReleaseId>
		        <ISRC>GX8KD2533338</ISRC>
		      </ReleaseId>
		      <ReleaseReference>R2</ReleaseReference>
		      <ReferenceTitle>
		        <TitleText>all nighter</TitleText></ReferenceTitle>
		      <ReleaseResourceReferenceList>
		        <ReleaseResourceReference ReleaseResourceType='PrimaryResource'>A2</ReleaseResourceReference>
		      </ReleaseResourceReferenceList>
		      <ReleaseType>TrackRelease</ReleaseType>
		      <ReleaseDetailsByTerritory>
		        <TerritoryCode>Worldwide</TerritoryCode>
		        <DisplayArtistName>kichmee</DisplayArtistName>
		        <LabelName>AK1MBO</LabelName><Title TitleType='FormalTitle'>
		          <TitleText>all nighter</TitleText>
		        </Title>
		        <Title TitleType='DisplayTitle'>
		          <TitleText>all nighter</TitleText>
		        </Title><DisplayArtist>
							<PartyName>
							<FullName>kichmee</FullName>
							</PartyName><ArtistRole>MainArtist</ArtistRole></DisplayArtist><DisplayArtist>
							<PartyName>
							<FullName>kichmee</FullName>
							</PartyName><ArtistRole>Producer</ArtistRole></DisplayArtist>
					 <Genre>
		          <GenreText>Hip Hop/Rap</GenreText>
				  <SubGenre>None</SubGenre>
		        </Genre>
		        <OriginalReleaseDate>2025-01-29</OriginalReleaseDate>
		      </ReleaseDetailsByTerritory>
			<PLine>
				<Year>2025</Year>
				<PLineText>AK1MBO</PLineText>
			 </PLine>
			 <CLine>
				<Year>2025</Year>
				<CLineText>AK1MBO</CLineText>
			</CLine>
			</Release>
		    <Release>
		      <ReleaseId>
		        <ISRC>GX8KD2510277</ISRC>
		      </ReleaseId>
		      <ReleaseReference>R3</ReleaseReference>
		      <ReferenceTitle>
		        <TitleText>fan</TitleText></ReferenceTitle>
		      <ReleaseResourceReferenceList>
		        <ReleaseResourceReference ReleaseResourceType='PrimaryResource'>A3</ReleaseResourceReference>
		      </ReleaseResourceReferenceList>
		      <ReleaseType>TrackRelease</ReleaseType>
		      <ReleaseDetailsByTerritory>
		        <TerritoryCode>Worldwide</TerritoryCode>
		        <DisplayArtistName>kichmee</DisplayArtistName>
		        <LabelName>AK1MBO</LabelName><Title TitleType='FormalTitle'>
		          <TitleText>fan</TitleText>
		        </Title>
		        <Title TitleType='DisplayTitle'>
		          <TitleText>fan</TitleText>
		        </Title><DisplayArtist>
							<PartyName>
							<FullName>kichmee</FullName>
							</PartyName><ArtistRole>MainArtist</ArtistRole></DisplayArtist><DisplayArtist>
							<PartyName>
							<FullName>jannychan</FullName>
							</PartyName><ArtistRole>Producer</ArtistRole></DisplayArtist>
					 <Genre>
		          <GenreText>Hip Hop/Rap</GenreText>
				  <SubGenre>None</SubGenre>
		        </Genre>
		        <OriginalReleaseDate>2025-01-29</OriginalReleaseDate>
		      </ReleaseDetailsByTerritory>
			<PLine>
				<Year>2025</Year>
				<PLineText>AK1MBO</PLineText>
			 </PLine>
			 <CLine>
				<Year>2025</Year>
				<CLineText>AK1MBO</CLineText>
			</CLine>
			</Release>
		    <Release IsMainRelease='true'>
		      <ReleaseId><ICPN IsEan='true'>5063687600036</ICPN><CatalogNumber Namespace='CDB'>kichmee</CatalogNumber></ReleaseId><ReleaseReference>R0</ReleaseReference>
			<ReferenceTitle><TitleText>bijeg iz kutije</TitleText></ReferenceTitle><ReleaseResourceReferenceList>
			  <ReleaseResourceReference ReleaseResourceType='PrimaryResource'>A1</ReleaseResourceReference>
			  
			  <ReleaseResourceReference ReleaseResourceType='PrimaryResource'>A2</ReleaseResourceReference>
			  
			  <ReleaseResourceReference ReleaseResourceType='PrimaryResource'>A3</ReleaseResourceReference>
			    <ReleaseResourceReference ReleaseResourceType='SecondaryResource'>A4</ReleaseResourceReference></ReleaseResourceReferenceList><ReleaseType>Album</ReleaseType> <ReleaseDetailsByTerritory>
		        <TerritoryCode>Worldwide</TerritoryCode>
		        <DisplayArtistName>kichmee</DisplayArtistName>
		        <LabelName>AK1MBO</LabelName>
					<Title TitleType='FormalTitle'>
					  <TitleText>bijeg iz kutije</TitleText>
					</Title>
					<Title TitleType='DisplayTitle'>
					  <TitleText>bijeg iz kutije</TitleText>
					</Title><DisplayArtist>
							<PartyName>
							<FullName>kichmee</FullName>
							</PartyName><ArtistRole>MainArtist</ArtistRole></DisplayArtist>
		        <ParentalWarningType>Explicit</ParentalWarningType>
				<ResourceGroup>
					<ResourceGroup>
						<Title TitleType='GroupingTitle'>
				          <TitleText>bijeg iz kutije</TitleText>
				  </Title><SequenceNumber>1</SequenceNumber><ResourceGroupContentItem>
				<SequenceNumber>1</SequenceNumber>
				<ResourceType>SoundRecording</ResourceType>
				<ReleaseResourceReference>A1</ReleaseResourceReference>
				</ResourceGroupContentItem><ResourceGroupContentItem>
				<SequenceNumber>2</SequenceNumber>
				<ResourceType>SoundRecording</ResourceType>
				<ReleaseResourceReference>A2</ReleaseResourceReference>
				</ResourceGroupContentItem><ResourceGroupContentItem>
				<SequenceNumber>3</SequenceNumber>
				<ResourceType>SoundRecording</ResourceType>
				<ReleaseResourceReference>A3</ReleaseResourceReference>
				</ResourceGroupContentItem> </ResourceGroup>
				  <ResourceGroupContentItem>
				 <ResourceType>Image</ResourceType>
				<ReleaseResourceReference>A4</ReleaseResourceReference>
				</ResourceGroupContentItem>
				</ResourceGroup>
		        <Genre>
		          <GenreText>Hip Hop/Rap</GenreText>
				  <SubGenre>None</SubGenre>
		        </Genre>
		        <OriginalReleaseDate>2025-01-29</OriginalReleaseDate>
		      </ReleaseDetailsByTerritory>
			<PLine>
				<Year>2025</Year>
				<PLineText>AK1MBO</PLineText>
			 </PLine>
			 <CLine>
				<Year>2025</Year>
				<CLineText>AK1MBO</CLineText>
			</CLine>
		    </Release></ReleaseList>
		  <DealList>
		    <ReleaseDeal>
		      <DealReleaseReference>R0</DealReleaseReference>
               <Deal>
		        <DealTerms>
					<CommercialModelType>PayAsYouGoModel</CommercialModelType>
                    <CommercialModelType>AdvertisementSupportedModel</CommercialModelType>
                     <CommercialModelType>SubscriptionModel</CommercialModelType> 
		         <Usage> 
                     <UseType>PermanentDownload</UseType> 
                     <UseType>OnDemandStream</UseType> 
                      <UseType>NonInteractiveStream</UseType> 
                      <DistributionChannelType>InternetAndMobile</DistributionChannelType> 
                 </Usage> 
					<TerritoryCode>Worldwide</TerritoryCode>
					<ValidityPeriod><StartDateTime>2025-02-25T20:00:00Z</StartDateTime></ValidityPeriod>
		        </DealTerms>
			</Deal>
		    </ReleaseDeal>
			<ReleaseDeal>
		      <DealReleaseReference>R1</DealReleaseReference>
		      <Deal>
		        <DealTerms>
					<CommercialModelType>PayAsYouGoModel</CommercialModelType>
                    <CommercialModelType>AdvertisementSupportedModel</CommercialModelType>
                    <CommercialModelType>SubscriptionModel</CommercialModelType> 
					<Usage> 
						 <UseType>PermanentDownload</UseType> 
                          <UseType>OnDemandStream</UseType> 
                          <UseType>NonInteractiveStream</UseType> 
                          <DistributionChannelType>InternetAndMobile</DistributionChannelType> 
                      </Usage>
					<TerritoryCode>Worldwide</TerritoryCode>
					<ValidityPeriod><StartDateTime>2025-02-25T20:00:00Z</StartDateTime></ValidityPeriod>
		        </DealTerms>
			</Deal>				  		      
		    </ReleaseDeal>
			<ReleaseDeal>
		      <DealReleaseReference>R2</DealReleaseReference>
		      <Deal>
		        <DealTerms>
					<CommercialModelType>PayAsYouGoModel</CommercialModelType>
                    <CommercialModelType>AdvertisementSupportedModel</CommercialModelType>
                    <CommercialModelType>SubscriptionModel</CommercialModelType> 
					<Usage> 
						 <UseType>PermanentDownload</UseType> 
                          <UseType>OnDemandStream</UseType> 
                          <UseType>NonInteractiveStream</UseType> 
                          <DistributionChannelType>InternetAndMobile</DistributionChannelType> 
                      </Usage>
					<TerritoryCode>Worldwide</TerritoryCode>
					<ValidityPeriod><StartDateTime>2025-02-25T20:00:00Z</StartDateTime></ValidityPeriod>
		        </DealTerms>
			</Deal>				  		      
		    </ReleaseDeal>
			<ReleaseDeal>
		      <DealReleaseReference>R3</DealReleaseReference>
		      <Deal>
		        <DealTerms>
					<CommercialModelType>PayAsYouGoModel</CommercialModelType>
                    <CommercialModelType>AdvertisementSupportedModel</CommercialModelType>
                    <CommercialModelType>SubscriptionModel</CommercialModelType> 
					<Usage> 
						 <UseType>PermanentDownload</UseType> 
                          <UseType>OnDemandStream</UseType> 
                          <UseType>NonInteractiveStream</UseType> 
                          <DistributionChannelType>InternetAndMobile</DistributionChannelType> 
                      </Usage>
					<TerritoryCode>Worldwide</TerritoryCode>
					<ValidityPeriod><StartDateTime>2025-02-25T20:00:00Z</StartDateTime></ValidityPeriod>
		        </DealTerms>
			</Deal>				  		      
		    </ReleaseDeal>
			</DealList></ern:NewReleaseMessage>